{"nm":"Main Scene","ddd":0,"h":600,"w":600,"meta":{"g":"@lottiefiles/creator 1.28.0"},"layers":[{"ty":0,"nm":"Nested Scene 5","sr":1,"st":58,"op":135,"ip":58,"hd":false,"ddd":0,"bm":0,"hasMask":false,"ao":0,"ks":{"a":{"a":0,"k":[299,301]},"s":{"a":1,"k":[{"o":{"x":0.167,"y":0.167},"i":{"x":0.833,"y":0.833},"s":[0,0],"t":63},{"s":[100,100],"t":84}]},"sk":{"a":0,"k":0},"p":{"a":0,"k":[299.9559,282.2441]},"r":{"a":0,"k":0},"sa":{"a":0,"k":0},"o":{"a":0,"k":100}},"w":600,"h":600,"refId":"precomp_newScene_fe949ba2-b608-4192-8084-c05f156f3270","ind":1},{"ty":0,"nm":"Nested Scene 5","sr":1,"st":0,"op":50,"ip":0,"hd":false,"ddd":0,"bm":0,"hasMask":false,"ao":0,"ks":{"a":{"a":0,"k":[300,300]},"s":{"a":1,"k":[{"o":{"x":0.167,"y":0.167},"i":{"x":0.833,"y":0.833},"s":[100,100],"t":24},{"s":[0,0],"t":53}]},"sk":{"a":0,"k":0},"p":{"a":0,"k":[300.3033,342.2697]},"r":{"a":0,"k":0},"sa":{"a":0,"k":0},"o":{"a":1,"k":[{"o":{"x":0.167,"y":0.167},"i":{"x":0.833,"y":0.833},"s":[100],"t":24},{"s":[0],"t":53}]}},"w":600,"h":600,"refId":"precomp_newScene_0d500caa-2b2b-4b99-955c-65a99d72fcf4","ind":2},{"ty":0,"nm":"Tie","sr":1,"st":102,"op":140,"ip":102,"hd":false,"ddd":0,"bm":0,"hasMask":false,"ao":0,"ks":{"a":{"a":0,"k":[299,304]},"s":{"a":0,"k":[100,100]},"sk":{"a":0,"k":0},"p":{"a":1,"k":[{"o":{"x":0.167,"y":0.167},"i":{"x":0.833,"y":0.833},"s":[300,-100],"t":55},{"o":{"x":0.167,"y":0.167},"i":{"x":0.833,"y":0.833},"s":[300,522.5],"t":134},{"s":[300,400.0587],"t":164}]},"r":{"a":0,"k":0},"sa":{"a":0,"k":0},"o":{"a":0,"k":100}},"w":600,"h":600,"refId":"precomp_newScene_4a103f38-2e4f-4cc1-a9c2-2284030c5811_7d762770-650f-4778-986d-4662403428a1","ind":3},{"ty":0,"nm":"Leaf","sr":1,"st":58,"op":140,"ip":58,"hd":false,"ddd":0,"bm":0,"hasMask":false,"ao":0,"ks":{"a":{"a":0,"k":[300,299.906]},"s":{"a":0,"k":[100,100]},"sk":{"a":0,"k":0},"p":{"a":0,"k":[300,278]},"r":{"a":0,"k":0},"sa":{"a":0,"k":0},"o":{"a":0,"k":100}},"w":597.5,"h":671.1569999999999,"refId":"precomp_newScene_09b270cb-4dba-4b5b-94d4-975249e8f4ea_a15d4f9f-b18f-4f35-9416-6eda134fca3f","ind":4}],"v":"5.7.0","fr":60,"op":135,"ip":0,"assets":[{"nm":"Nested Scene 3","id":"precomp_newScene_09b270cb-4dba-4b5b-94d4-975249e8f4ea_a15d4f9f-b18f-4f35-9416-6eda134fca3f","layers":[{"ty":4,"nm":"Capa 12","sr":1,"st":0,"op":80,"ip":0,"hd":false,"ddd":0,"bm":0,"hasMask":false,"ao":0,"ks":{"a":{"a":0,"k":[-76,-18,0]},"s":{"a":1,"k":[{"o":{"x":0.333,"y":0},"i":{"x":0.667,"y":1},"s":[0,0,100],"t":0},{"o":{"x":0.333,"y":0},"i":{"x":0.667,"y":1},"s":[110,110,100],"t":14},{"s":[100,100,100],"t":22}]},"sk":{"a":0,"k":0},"p":{"a":0,"k":[320.393,457.799,0]},"r":{"a":0,"k":0},"sa":{"a":0,"k":0},"o":{"a":0,"k":100}},"shapes":[{"ty":"gr","bm":0,"hd":false,"mn":"ADBE Vector Group","nm":"Group 1","ix":1,"cix":2,"np":2,"it":[{"ty":"sh","bm":0,"hd":false,"mn":"ADBE Vector Shape - Group","nm":"Path 1","ix":1,"d":1,"ks":{"a":0,"k":{"c":true,"i":[[-7.174,4.142],[0,0],[-17.423,-30.18],[0,0],[7.175,-4.142],[0,0],[17.424,30.18],[0,0]],"o":[[0,0],[30.18,-17.424],[0,0],[4.142,7.174],[0,0],[-30.18,17.424],[0,0],[-4.14,-7.174]],"v":[[-73.342,-30.634],[-31.599,-54.733],[54.733,-31.599],[78.832,10.144],[73.341,30.634],[31.598,54.733],[-54.735,31.599],[-78.834,-10.144]]}}},{"ty":"fl","bm":0,"hd":false,"mn":"ADBE Vector Graphic - Fill","nm":"Fill 1","c":{"a":0,"k":[0.8824,0.8824,0.8824]},"r":1,"o":{"a":0,"k":100}},{"ty":"tr","a":{"a":0,"k":[0,0]},"s":{"a":0,"k":[100,100]},"sk":{"a":0,"k":0},"p":{"a":0,"k":[0,0]},"r":{"a":0,"k":0},"sa":{"a":0,"k":0},"o":{"a":0,"k":100}}]}],"ind":1},{"ty":4,"nm":"Capa 11","sr":1,"st":0,"op":80,"ip":0,"hd":false,"ddd":0,"bm":0,"hasMask":false,"ao":0,"ks":{"a":{"a":0,"k":[-76.5,21,0]},"s":{"a":1,"k":[{"o":{"x":0.333,"y":0},"i":{"x":0.667,"y":1},"s":[0,0,100],"t":4},{"o":{"x":0.333,"y":0},"i":{"x":0.667,"y":1},"s":[110,110,100],"t":18},{"s":[100,100,100],"t":26}]},"sk":{"a":0,"k":0},"p":{"a":0,"k":[390.464,426.228,0]},"r":{"a":0,"k":0},"sa":{"a":0,"k":0},"o":{"a":0,"k":100}},"shapes":[{"ty":"gr","bm":0,"hd":false,"mn":"ADBE Vector Group","nm":"Group 1","ix":1,"cix":2,"np":2,"it":[{"ty":"sh","bm":0,"hd":false,"mn":"ADBE Vector Shape - Group","nm":"Path 1","ix":1,"d":1,"ks":{"a":0,"k":{"c":true,"i":[[-4.142,7.175],[0,0],[-30.18,-17.425],[0,0],[4.143,-7.174],[0,0],[30.18,17.424],[0,0]],"o":[[0,0],[17.424,-30.18],[0,0],[7.174,4.142],[0,0],[-17.424,30.18],[0,0],[-7.175,-4.142]],"v":[[-78.833,10.143],[-54.733,-31.6],[31.6,-54.733],[73.343,-30.633],[78.833,-10.143],[54.733,31.6],[-31.6,54.733],[-73.342,30.633]]}}},{"ty":"fl","bm":0,"hd":false,"mn":"ADBE Vector Graphic - Fill","nm":"Fill 1","c":{"a":0,"k":[0.9373,0.9373,0.9373]},"r":1,"o":{"a":0,"k":100}},{"ty":"tr","a":{"a":0,"k":[0,0]},"s":{"a":0,"k":[100,100]},"sk":{"a":0,"k":0},"p":{"a":0,"k":[0,0]},"r":{"a":0,"k":0},"sa":{"a":0,"k":0},"o":{"a":0,"k":100}}]}],"ind":2},{"ty":4,"nm":"Capa 10","sr":1,"st":0,"op":80,"ip":0,"hd":false,"ddd":0,"bm":0,"hasMask":false,"ao":0,"ks":{"a":{"a":0,"k":[-55.5,52,0]},"s":{"a":1,"k":[{"o":{"x":0.333,"y":0},"i":{"x":0.667,"y":1},"s":[0,0,100],"t":8},{"o":{"x":0.333,"y":0},"i":{"x":0.667,"y":1},"s":[110,110,100],"t":22},{"s":[100,100,100],"t":30}]},"sk":{"a":0,"k":0},"p":{"a":0,"k":[437.3,360.828,0]},"r":{"a":0,"k":0},"sa":{"a":0,"k":0},"o":{"a":0,"k":100}},"shapes":[{"ty":"gr","bm":0,"hd":false,"mn":"ADBE Vector Group","nm":"Group 1","ix":1,"cix":2,"np":2,"it":[{"ty":"sh","bm":0,"hd":false,"mn":"ADBE Vector Shape - Group","nm":"Path 1","ix":1,"d":1,"ks":{"a":0,"k":{"c":true,"i":[[0,0],[0,0],[0,34.848],[0,0],[8.284,0],[0,0],[0,-34.848],[0,0],[-8.284,0]],"o":[[0,0],[34.849,0],[0,0],[0,-8.284],[0,0],[-34.849,0],[0,0],[0,8.285],[0,0]],"v":[[-48.2,63.2],[0,63.2],[63.2,0],[63.2,-48.2],[48.2,-63.2],[0,-63.2],[-63.2,0],[-63.2,48.2],[-48.2,63.2]]}}},{"ty":"fl","bm":0,"hd":false,"mn":"ADBE Vector Graphic - Fill","nm":"Fill 1","c":{"a":0,"k":[0.8039,0.8039,0.8039]},"r":1,"o":{"a":0,"k":100}},{"ty":"tr","a":{"a":0,"k":[0,0]},"s":{"a":0,"k":[100,100]},"sk":{"a":0,"k":0},"p":{"a":0,"k":[0,0]},"r":{"a":0,"k":0},"sa":{"a":0,"k":0},"o":{"a":0,"k":100}}]}],"ind":3},{"ty":4,"nm":"Capa 9","sr":1,"st":0,"op":80,"ip":0,"hd":false,"ddd":0,"bm":0,"hasMask":false,"ao":0,"ks":{"a":{"a":0,"k":[-20,73,0]},"s":{"a":1,"k":[{"o":{"x":0.333,"y":0},"i":{"x":0.667,"y":1},"s":[0,0,100],"t":12},{"o":{"x":0.333,"y":0},"i":{"x":0.667,"y":1},"s":[110,110,100],"t":26},{"s":[100,100,100],"t":34}]},"sk":{"a":0,"k":0},"p":{"a":0,"k":[446.964,285.428,0]},"r":{"a":0,"k":0},"sa":{"a":0,"k":0},"o":{"a":0,"k":100}},"shapes":[{"ty":"gr","bm":0,"hd":false,"mn":"ADBE Vector Group","nm":"Group 1","ix":1,"cix":2,"np":2,"it":[{"ty":"sh","bm":0,"hd":false,"mn":"ADBE Vector Shape - Group","nm":"Path 1","ix":1,"d":1,"ks":{"a":0,"k":{"c":true,"i":[[30.18,-17.424],[0,0],[4.142,7.174],[0,0],[-30.18,17.425],[0,0],[-4.142,-7.174],[0,0]],"o":[[0,0],[-7.174,4.142],[0,0],[-17.424,-30.18],[0,0],[7.174,-4.142],[0,0],[17.425,30.181]],"v":[[31.6,54.733],[-10.142,78.833],[-30.632,73.343],[-54.732,31.6],[-31.6,-54.733],[10.142,-78.833],[30.632,-73.343],[54.732,-31.601]]}}},{"ty":"fl","bm":0,"hd":false,"mn":"ADBE Vector Graphic - Fill","nm":"Fill 1","c":{"a":0,"k":[0.9373,0.9373,0.9373]},"r":1,"o":{"a":0,"k":100}},{"ty":"tr","a":{"a":0,"k":[0,0]},"s":{"a":0,"k":[100,100]},"sk":{"a":0,"k":0},"p":{"a":0,"k":[0,0]},"r":{"a":0,"k":0},"sa":{"a":0,"k":0},"o":{"a":0,"k":100}}]}],"ind":4},{"ty":4,"nm":"Capa 8","sr":1,"st":0,"op":80,"ip":0,"hd":false,"ddd":0,"bm":0,"hasMask":false,"ao":0,"ks":{"a":{"a":0,"k":[17.5,69.5,0]},"s":{"a":1,"k":[{"o":{"x":0.333,"y":0},"i":{"x":0.667,"y":1},"s":[0,0,100],"t":16},{"o":{"x":0.333,"y":0},"i":{"x":0.667,"y":1},"s":[110,110,100],"t":30},{"s":[100,100,100],"t":38}]},"sk":{"a":0,"k":0},"p":{"a":0,"k":[413.899,211.358,0]},"r":{"a":0,"k":0},"sa":{"a":0,"k":0},"o":{"a":0,"k":100}},"shapes":[{"ty":"gr","bm":0,"hd":false,"mn":"ADBE Vector Group","nm":"Group 1","ix":1,"cix":2,"np":2,"it":[{"ty":"sh","bm":0,"hd":false,"mn":"ADBE Vector Shape - Group","nm":"Path 1","ix":1,"d":1,"ks":{"a":0,"k":{"c":true,"i":[[0,0],[7.174,4.142],[0,0],[-17.423,30.18],[0,0],[-7.175,-4.141],[0,0],[17.422,-30.181]],"o":[[-4.142,7.174],[0,0],[-30.181,-17.423],[0,0],[4.142,-7.175],[0,0],[30.181,17.423],[0,0]],"v":[[30.637,73.341],[10.147,78.832],[-31.597,54.734],[-54.735,-31.597],[-30.637,-73.341],[-10.147,-78.833],[31.597,-54.735],[54.735,31.597]]}}},{"ty":"fl","bm":0,"hd":false,"mn":"ADBE Vector Graphic - Fill","nm":"Fill 1","c":{"a":0,"k":[0.8824,0.8824,0.8824]},"r":1,"o":{"a":0,"k":100}},{"ty":"tr","a":{"a":0,"k":[0,0]},"s":{"a":0,"k":[100,100]},"sk":{"a":0,"k":0},"p":{"a":0,"k":[0,0]},"r":{"a":0,"k":0},"sa":{"a":0,"k":0},"o":{"a":0,"k":100}}]}],"ind":5},{"ty":4,"nm":"Capa 7","sr":1,"st":0,"op":80,"ip":0,"hd":false,"ddd":0,"bm":0,"hasMask":false,"ao":0,"ks":{"a":{"a":0,"k":[69,-16,0]},"s":{"a":1,"k":[{"o":{"x":0.333,"y":0},"i":{"x":0.667,"y":1},"s":[0,0,100],"t":4},{"o":{"x":0.333,"y":0},"i":{"x":0.667,"y":1},"s":[110,110,100],"t":18},{"s":[100,100,100],"t":26}]},"sk":{"a":0,"k":0},"p":{"a":0,"k":[272.607,459.799,0]},"r":{"a":0,"k":0},"sa":{"a":0,"k":0},"o":{"a":0,"k":100}},"shapes":[{"ty":"gr","bm":0,"hd":false,"mn":"ADBE Vector Group","nm":"Group 1","ix":1,"cix":2,"np":2,"it":[{"ty":"sh","bm":0,"hd":false,"mn":"ADBE Vector Shape - Group","nm":"Path 1","ix":1,"d":1,"ks":{"a":0,"k":{"c":true,"i":[[7.174,4.142],[0,0],[17.423,-30.18],[0,0],[-7.175,-4.142],[0,0],[-17.424,30.18],[0,0]],"o":[[0,0],[-30.18,-17.424],[0,0],[-4.142,7.174],[0,0],[30.18,17.424],[0,0],[4.14,-7.174]],"v":[[73.342,-30.634],[31.599,-54.733],[-54.733,-31.599],[-78.832,10.144],[-73.341,30.634],[-31.598,54.733],[54.735,31.599],[78.834,-10.144]]}}},{"ty":"fl","bm":0,"hd":false,"mn":"ADBE Vector Graphic - Fill","nm":"Fill 1","c":{"a":0,"k":[0.8078,0.8078,0.8078]},"r":1,"o":{"a":0,"k":100}},{"ty":"tr","a":{"a":0,"k":[0,0]},"s":{"a":0,"k":[100,100]},"sk":{"a":0,"k":0},"p":{"a":0,"k":[0,0]},"r":{"a":0,"k":0},"sa":{"a":0,"k":0},"o":{"a":0,"k":100}}]}],"ind":6},{"ty":4,"nm":"Capa 6","sr":1,"st":0,"op":80,"ip":0,"hd":false,"ddd":0,"bm":0,"hasMask":false,"ao":0,"ks":{"a":{"a":0,"k":[72,20,0]},"s":{"a":1,"k":[{"o":{"x":0.333,"y":0},"i":{"x":0.667,"y":1},"s":[0,0,100],"t":8},{"o":{"x":0.333,"y":0},"i":{"x":0.667,"y":1},"s":[110,110,100],"t":22},{"s":[100,100,100],"t":30}]},"sk":{"a":0,"k":0},"p":{"a":0,"k":[205.036,425.228,0]},"r":{"a":0,"k":0},"sa":{"a":0,"k":0},"o":{"a":0,"k":100}},"shapes":[{"ty":"gr","bm":0,"hd":false,"mn":"ADBE Vector Group","nm":"Group 1","ix":1,"cix":2,"np":2,"it":[{"ty":"sh","bm":0,"hd":false,"mn":"ADBE Vector Shape - Group","nm":"Path 1","ix":1,"d":1,"ks":{"a":0,"k":{"c":true,"i":[[4.142,7.175],[0,0],[30.18,-17.425],[0,0],[-4.143,-7.174],[0,0],[-30.18,17.424],[0,0]],"o":[[0,0],[-17.424,-30.18],[0,0],[-7.174,4.142],[0,0],[17.424,30.18],[0,0],[7.175,-4.142]],"v":[[78.833,10.143],[54.733,-31.6],[-31.6,-54.733],[-73.343,-30.633],[-78.833,-10.143],[-54.733,31.6],[31.6,54.733],[73.342,30.633]]}}},{"ty":"fl","bm":0,"hd":false,"mn":"ADBE Vector Graphic - Fill","nm":"Fill 1","c":{"a":0,"k":[0.8824,0.8824,0.8824]},"r":1,"o":{"a":0,"k":100}},{"ty":"tr","a":{"a":0,"k":[0,0]},"s":{"a":0,"k":[100,100]},"sk":{"a":0,"k":0},"p":{"a":0,"k":[0,0]},"r":{"a":0,"k":0},"sa":{"a":0,"k":0},"o":{"a":0,"k":100}}]}],"ind":7},{"ty":4,"nm":"Capa 5","sr":1,"st":0,"op":80,"ip":0,"hd":false,"ddd":0,"bm":0,"hasMask":false,"ao":0,"ks":{"a":{"a":0,"k":[51.5,52.5,0]},"s":{"a":1,"k":[{"o":{"x":0.333,"y":0},"i":{"x":0.667,"y":1},"s":[0,0,100],"t":12},{"o":{"x":0.333,"y":0},"i":{"x":0.667,"y":1},"s":[110,110,100],"t":26},{"s":[100,100,100],"t":34}]},"sk":{"a":0,"k":0},"p":{"a":0,"k":[158.7,361.328,0]},"r":{"a":0,"k":0},"sa":{"a":0,"k":0},"o":{"a":0,"k":100}},"shapes":[{"ty":"gr","bm":0,"hd":false,"mn":"ADBE Vector Group","nm":"Group 1","ix":1,"cix":2,"np":2,"it":[{"ty":"sh","bm":0,"hd":false,"mn":"ADBE Vector Shape - Group","nm":"Path 1","ix":1,"d":1,"ks":{"a":0,"k":{"c":true,"i":[[8.284,0],[0,0],[0,34.848],[0,0],[-8.284,0],[0,0],[0,-34.848],[0,0]],"o":[[0,0],[-34.849,0],[0,0],[0,-8.284],[0,0],[34.849,0],[0,0],[0,8.285]],"v":[[48.2,63.2],[0,63.2],[-63.2,0],[-63.2,-48.2],[-48.2,-63.2],[0,-63.2],[63.2,0],[63.2,48.2]]}}},{"ty":"fl","bm":0,"hd":false,"mn":"ADBE Vector Graphic - Fill","nm":"Fill 1","c":{"a":0,"k":[0.9373,0.9373,0.9373]},"r":1,"o":{"a":0,"k":100}},{"ty":"tr","a":{"a":0,"k":[0,0]},"s":{"a":0,"k":[100,100]},"sk":{"a":0,"k":0},"p":{"a":0,"k":[0,0]},"r":{"a":0,"k":0},"sa":{"a":0,"k":0},"o":{"a":0,"k":100}}]}],"ind":8},{"ty":4,"nm":"Capa 4","sr":1,"st":0,"op":80,"ip":0,"hd":false,"ddd":0,"bm":0,"hasMask":false,"ao":0,"ks":{"a":{"a":0,"k":[17.5,73,0]},"s":{"a":1,"k":[{"o":{"x":0.333,"y":0},"i":{"x":0.667,"y":1},"s":[0,0,100],"t":16},{"o":{"x":0.333,"y":0},"i":{"x":0.667,"y":1},"s":[110,110,100],"t":30},{"s":[100,100,100],"t":38}]},"sk":{"a":0,"k":0},"p":{"a":0,"k":[150.536,285.428,0]},"r":{"a":0,"k":0},"sa":{"a":0,"k":0},"o":{"a":0,"k":100}},"shapes":[{"ty":"gr","bm":0,"hd":false,"mn":"ADBE Vector Group","nm":"Group 1","ix":1,"cix":2,"np":2,"it":[{"ty":"sh","bm":0,"hd":false,"mn":"ADBE Vector Shape - Group","nm":"Path 1","ix":1,"d":1,"ks":{"a":0,"k":{"c":true,"i":[[-30.18,-17.424],[0,0],[-4.142,7.174],[0,0],[30.18,17.425],[0,0],[4.142,-7.174],[0,0]],"o":[[0,0],[7.174,4.142],[0,0],[17.424,-30.18],[0,0],[-7.174,-4.142],[0,0],[-17.425,30.181]],"v":[[-31.6,54.733],[10.142,78.833],[30.632,73.343],[54.732,31.6],[31.6,-54.733],[-10.142,-78.833],[-30.632,-73.343],[-54.732,-31.601]]}}},{"ty":"fl","bm":0,"hd":false,"mn":"ADBE Vector Graphic - Fill","nm":"Fill 1","c":{"a":0,"k":[0.8824,0.8824,0.8824]},"r":1,"o":{"a":0,"k":100}},{"ty":"tr","a":{"a":0,"k":[0,0]},"s":{"a":0,"k":[100,100]},"sk":{"a":0,"k":0},"p":{"a":0,"k":[0,0]},"r":{"a":0,"k":0},"sa":{"a":0,"k":0},"o":{"a":0,"k":100}}]}],"ind":9},{"ty":4,"nm":"Capa 3","sr":1,"st":0,"op":80,"ip":0,"hd":false,"ddd":0,"bm":0,"hasMask":false,"ao":0,"ks":{"a":{"a":0,"k":[-21.5,74.5,0]},"s":{"a":1,"k":[{"o":{"x":0.333,"y":0},"i":{"x":0.667,"y":1},"s":[0,0,100],"t":20},{"o":{"x":0.333,"y":0},"i":{"x":0.667,"y":1},"s":[110,110,100],"t":34},{"s":[100,100,100],"t":42}]},"sk":{"a":0,"k":0},"p":{"a":0,"k":[182.101,216.358,0]},"r":{"a":0,"k":0},"sa":{"a":0,"k":0},"o":{"a":0,"k":100}},"shapes":[{"ty":"gr","bm":0,"hd":false,"mn":"ADBE Vector Group","nm":"Group 1","ix":1,"cix":2,"np":2,"it":[{"ty":"sh","bm":0,"hd":false,"mn":"ADBE Vector Shape - Group","nm":"Path 1","ix":1,"d":1,"ks":{"a":0,"k":{"c":true,"i":[[0,0],[-7.174,4.142],[0,0],[17.423,30.18],[0,0],[7.175,-4.141],[0,0],[-17.422,-30.181]],"o":[[4.142,7.174],[0,0],[30.181,-17.423],[0,0],[-4.142,-7.175],[0,0],[-30.181,17.423],[0,0]],"v":[[-30.637,73.341],[-10.147,78.832],[31.597,54.734],[54.735,-31.597],[30.637,-73.341],[10.147,-78.833],[-31.597,-54.735],[-54.735,31.597]]}}},{"ty":"fl","bm":0,"hd":false,"mn":"ADBE Vector Graphic - Fill","nm":"Fill 1","c":{"a":0,"k":[0.8078,0.8078,0.8078]},"r":1,"o":{"a":0,"k":100}},{"ty":"tr","a":{"a":0,"k":[0,0]},"s":{"a":0,"k":[100,100]},"sk":{"a":0,"k":0},"p":{"a":0,"k":[0,0]},"r":{"a":0,"k":0},"sa":{"a":0,"k":0},"o":{"a":0,"k":100}}]}],"ind":10},{"ty":4,"nm":"Leaf 2","sr":1,"st":0,"op":80,"ip":0,"hd":false,"ddd":0,"bm":0,"hasMask":false,"ao":0,"ks":{"a":{"a":0,"k":[0,0,0]},"s":{"a":0,"k":[-100,100,100]},"sk":{"a":0,"k":0},"p":{"a":0,"k":[311,300,0]},"r":{"a":0,"k":0},"sa":{"a":0,"k":0},"o":{"a":0,"k":100}},"shapes":[{"ty":"gr","bm":0,"hd":false,"mn":"ADBE Vector Group","nm":"Shape 1","ix":1,"cix":2,"np":3,"it":[{"ty":"sh","bm":0,"hd":false,"mn":"ADBE Vector Shape - Group","nm":"Path 1","ix":1,"d":1,"ks":{"a":0,"k":{"c":false,"i":[[0,0],[197.351,259.264]],"o":[[0,0],[-51,-67]],"v":[[8,176],[121,-155]]}}},{"ty":"st","bm":0,"hd":false,"mn":"ADBE Vector Graphic - Stroke","nm":"Stroke 1","lc":1,"lj":1,"ml":4,"o":{"a":0,"k":100},"w":{"a":0,"k":30},"c":{"a":0,"k":[0.8902,0.8902,0.8902]}},{"ty":"tr","a":{"a":0,"k":[0,0]},"s":{"a":0,"k":[100,100]},"sk":{"a":0,"k":0},"p":{"a":0,"k":[0,0]},"r":{"a":0,"k":0},"sa":{"a":0,"k":0},"o":{"a":0,"k":100}}]},{"ty":"tm","bm":0,"hd":false,"mn":"ADBE Vector Filter - Trim","nm":"Trim Paths 1","ix":2,"e":{"a":1,"k":[{"o":{"x":0.333,"y":0},"i":{"x":0.667,"y":1},"s":[0],"t":0},{"s":[100],"t":42}]},"o":{"a":0,"k":0},"s":{"a":0,"k":0},"m":1}],"ind":11},{"ty":4,"nm":"Leaf","sr":1,"st":0,"op":80,"ip":0,"hd":false,"ddd":0,"bm":0,"hasMask":false,"ao":0,"ks":{"a":{"a":0,"k":[0,0,0]},"s":{"a":0,"k":[100,100,100]},"sk":{"a":0,"k":0},"p":{"a":0,"k":[287,300,0]},"r":{"a":0,"k":0},"sa":{"a":0,"k":0},"o":{"a":0,"k":100}},"shapes":[{"ty":"gr","bm":0,"hd":false,"mn":"ADBE Vector Group","nm":"Shape 1","ix":1,"cix":2,"np":3,"it":[{"ty":"sh","bm":0,"hd":false,"mn":"ADBE Vector Shape - Group","nm":"Path 1","ix":1,"d":1,"ks":{"a":0,"k":{"c":false,"i":[[0,0],[197.351,259.264]],"o":[[0,0],[-51,-67]],"v":[[8,176],[121,-155]]}}},{"ty":"st","bm":0,"hd":false,"mn":"ADBE Vector Graphic - Stroke","nm":"Stroke 1","lc":1,"lj":1,"ml":4,"o":{"a":0,"k":100},"w":{"a":0,"k":30},"c":{"a":0,"k":[0.8902,0.8902,0.8902]}},{"ty":"tr","a":{"a":0,"k":[0,0]},"s":{"a":0,"k":[100,100]},"sk":{"a":0,"k":0},"p":{"a":0,"k":[0,0]},"r":{"a":0,"k":0},"sa":{"a":0,"k":0},"o":{"a":0,"k":100}}]},{"ty":"tm","bm":0,"hd":false,"mn":"ADBE Vector Filter - Trim","nm":"Trim Paths 1","ix":2,"e":{"a":1,"k":[{"o":{"x":0.333,"y":0},"i":{"x":0.667,"y":1},"s":[0],"t":0},{"s":[100],"t":42}]},"o":{"a":0,"k":0},"s":{"a":0,"k":0},"m":1}],"ind":12}]},{"nm":"Nested Scene 4","id":"precomp_newScene_4a103f38-2e4f-4cc1-a9c2-2284030c5811_7d762770-650f-4778-986d-4662403428a1","layers":[{"ty":4,"nm":"Shape Layer 1","sr":1,"st":0,"op":80,"ip":0,"hd":false,"ddd":0,"bm":0,"hasMask":false,"ao":0,"ks":{"a":{"a":0,"k":[151.5,99]},"s":{"a":0,"k":[100,100]},"sk":{"a":0,"k":0},"p":{"a":0,"k":[344,317]},"r":{"a":0,"k":0},"sa":{"a":0,"k":0},"o":{"a":0,"k":100}},"shapes":[{"ty":"gr","bm":0,"hd":false,"nm":"Group 1","it":[{"ty":"sh","bm":0,"hd":false,"nm":"Path 1","d":1,"ks":{"a":0,"k":{"c":true,"i":[[0,0],[-0.6670000000000016,0],[0.6740000000000066,-30.236000000000004],[0,30],[0,0.33330000000000126]],"o":[[0.6670000000000016,0],[-0.6589999999999918,30.4311],[0,-30],[0,-0.33330000000000126],[0,0]],"v":[[150.5,53.5],[152.5,53.5],[150.5,144.5],[150.5,54.5],[150.5,53.5]]}}},{"ty":"fl","bm":0,"hd":false,"nm":"Fill","c":{"a":0,"k":[0.9569,0.9451,0.9451]},"r":2,"o":{"a":0,"k":100}},{"ty":"tr","a":{"a":0,"k":[0,0]},"s":{"a":0,"k":[100,100]},"sk":{"a":0,"k":0},"p":{"a":0,"k":[0,0]},"r":{"a":0,"k":0},"sa":{"a":0,"k":0},"o":{"a":0,"k":99.5}}]}],"ind":1},{"ty":4,"nm":"Shape Layer 3","sr":1,"st":0,"op":80,"ip":0,"hd":false,"ddd":0,"bm":0,"hasMask":false,"ao":0,"ks":{"a":{"a":0,"k":[0,0]},"s":{"a":0,"k":[100,100]},"sk":{"a":0,"k":0},"p":{"a":0,"k":[192.5,218]},"r":{"a":0,"k":0},"sa":{"a":0,"k":0},"o":{"a":0,"k":100}},"shapes":[{"ty":"gr","bm":0,"hd":false,"nm":"Group 3","it":[{"ty":"sh","bm":0,"hd":false,"nm":"Path 3","d":1,"ks":{"a":0,"k":{"c":true,"i":[[0,0],[0,-38.333],[1,0],[13.8489,5.431000000000012],[0,30.666700000000006],[-6.627600000000001,1.0523000000000025],[-8.067499999999995,1.046599999999998]],"o":[[0,38.333299999999994],[-1,0],[-13.484499999999997,-5.902999999999992],[0,-30.667],[6.705699999999993,0.052300000000002456],[7.9325000000000045,-1.953400000000002],[0,0]],"v":[[106.5,48.5],[106.5,163.5],[103.5,163.5],[62.5,146.5],[62.5,54.5],[82.5,53],[106.5,48.5]]}}},{"ty":"fl","bm":0,"hd":false,"nm":"Fill","c":{"a":0,"k":[0.9647,0.9569,0.9569]},"r":2,"o":{"a":0,"k":100}},{"ty":"tr","a":{"a":0,"k":[0,0]},"s":{"a":0,"k":[100,100]},"sk":{"a":0,"k":0},"p":{"a":0,"k":[0,0]},"r":{"a":0,"k":0},"sa":{"a":0,"k":0},"o":{"a":0,"k":99.6}}]}],"ind":2},{"ty":4,"nm":"Shape Layer 2","sr":1,"st":0,"op":80,"ip":0,"hd":false,"ddd":0,"bm":0,"hasMask":false,"ao":0,"ks":{"a":{"a":0,"k":[0,0]},"s":{"a":0,"k":[100,100]},"sk":{"a":0,"k":0},"p":{"a":0,"k":[192.5,218]},"r":{"a":0,"k":0},"sa":{"a":0,"k":0},"o":{"a":0,"k":100}},"shapes":[{"ty":"gr","bm":0,"hd":false,"nm":"Group 2","it":[{"ty":"sh","bm":0,"hd":false,"nm":"Path 2","d":1,"ks":{"a":0,"k":{"c":true,"i":[[0,0],[-9.607,-2.267400000000002],[-5.010999999999996,0.1659000000000006],[0,-30],[0,-0.6670000000000016],[13.483999999999995,-5.902999999999992],[1,0],[0,38.333299999999994]],"o":[[9.725999999999999,1.3992999999999967],[4.989000000000004,0.4992999999999981],[0,30],[0,0.6670000000000016],[-13.84899999999999,5.431000000000012],[-1,0],[0,-38.333],[0,0]],"v":[[106.5,48.5],[135.5,54],[150.5,54.5],[150.5,144.5],[150.5,146.5],[109.5,163.5],[106.5,163.5],[106.5,48.5]]}}},{"ty":"fl","bm":0,"hd":false,"nm":"Fill","c":{"a":0,"k":[0.9373,0.9098,0.9098]},"r":2,"o":{"a":0,"k":100}},{"ty":"tr","a":{"a":0,"k":[0,0]},"s":{"a":0,"k":[100,100]},"sk":{"a":0,"k":0},"p":{"a":0,"k":[0,0]},"r":{"a":0,"k":0},"sa":{"a":0,"k":0},"o":{"a":0,"k":99.7}}]}],"ind":3},{"ty":4,"nm":"Shape Layer 4","sr":1,"st":0,"op":80,"ip":0,"hd":false,"ddd":0,"bm":0,"hasMask":false,"ao":0,"ks":{"a":{"a":0,"k":[0,0]},"s":{"a":0,"k":[100,100]},"sk":{"a":0,"k":0},"p":{"a":0,"k":[192.5,218]},"r":{"a":0,"k":0},"sa":{"a":0,"k":0},"o":{"a":0,"k":100}},"shapes":[{"ty":"gr","bm":0,"hd":false,"nm":"Group 4","it":[{"ty":"sh","bm":0,"hd":false,"nm":"Path 4","d":1,"ks":{"a":0,"k":{"c":true,"i":[[0,0],[-10.581000000000003,-2.416499999999999],[-3.962999999999994,0.9399999999999977],[0,-6],[0,-0.33330000000000126],[4.989000000000004,0.4992999999999981],[9.725999999999999,1.3992999999999967],[0,6]],"o":[[10.753,1.2501999999999995],[4.037000000000006,0.6066999999999965],[0,6],[0,0.33330000000000126],[-5.010999999999996,0.1659000000000006],[-9.607,-2.267400000000002],[0,-6],[0,0]],"v":[[106.5,30.5],[138.5,36],[150.5,35.5],[150.5,53.5],[150.5,54.5],[135.5,54],[106.5,48.5],[106.5,30.5]]}}},{"ty":"fl","bm":0,"hd":false,"nm":"Fill","c":{"a":0,"k":[0.898,0.8667,0.8627]},"r":2,"o":{"a":0,"k":100}},{"ty":"tr","a":{"a":0,"k":[0,0]},"s":{"a":0,"k":[100,100]},"sk":{"a":0,"k":0},"p":{"a":0,"k":[0,0]},"r":{"a":0,"k":0},"sa":{"a":0,"k":0},"o":{"a":0,"k":100}}]}],"ind":4},{"ty":4,"nm":"Shape Layer 5","sr":1,"st":0,"op":80,"ip":0,"hd":false,"ddd":0,"bm":0,"hasMask":false,"ao":0,"ks":{"a":{"a":0,"k":[0,0]},"s":{"a":0,"k":[100,100]},"sk":{"a":0,"k":0},"p":{"a":0,"k":[192.5,218]},"r":{"a":0,"k":0},"sa":{"a":0,"k":0},"o":{"a":0,"k":100}},"shapes":[{"ty":"gr","bm":0,"hd":false,"nm":"Group 5","it":[{"ty":"sh","bm":0,"hd":false,"nm":"Path 5","d":1,"ks":{"a":0,"k":{"c":true,"i":[[0,0],[0,-45],[1,0],[14.23599999999999,5.295999999999992],[0,0.6670000000000016],[-0.6589999999999918,30.4311],[-3.929000000000002,1.4771],[-9.955999999999989,7.649999999999999]],"o":[[0,45],[-1,0],[-13.76400000000001,-6.038000000000011],[0,-0.6670000000000016],[0.6740000000000066,-30.236000000000004],[4.070999999999998,-0.8562000000000012],[10.711000000000013,-6.683300000000003],[0,0]],"v":[[195.5,28.5],[195.5,163.5],[192.5,163.5],[150.5,146.5],[150.5,144.5],[152.5,53.5],[164.5,50],[195.5,28.5]]}}},{"ty":"fl","bm":0,"hd":false,"nm":"Fill","c":{"a":0,"k":[0.9647,0.9569,0.9569]},"r":2,"o":{"a":0,"k":100}},{"ty":"tr","a":{"a":0,"k":[0,0]},"s":{"a":0,"k":[100,100]},"sk":{"a":0,"k":0},"p":{"a":0,"k":[0,0]},"r":{"a":0,"k":0},"sa":{"a":0,"k":0},"o":{"a":0,"k":98.5}}]}],"ind":5},{"ty":4,"nm":"Shape Layer 6","sr":1,"st":0,"op":80,"ip":0,"hd":false,"ddd":0,"bm":0,"hasMask":false,"ao":0,"ks":{"a":{"a":0,"k":[0,0]},"s":{"a":0,"k":[100,100]},"sk":{"a":0,"k":0},"p":{"a":0,"k":[192.5,218]},"r":{"a":0,"k":0},"sa":{"a":0,"k":0},"o":{"a":0,"k":100}},"shapes":[{"ty":"gr","bm":0,"hd":false,"nm":"Group 6","it":[{"ty":"sh","bm":0,"hd":false,"nm":"Path 6","d":1,"ks":{"a":0,"k":{"c":true,"i":[[0,0],[-7.878100000000003,-6.051400000000001],[-7.572899999999997,-0.7813999999999979],[0,6],[-2.3182999999999936,-0.4971000000000032],[-12.396600000000007,1.5144999999999982],[0,-6],[7.9325000000000045,-1.953400000000002],[6.705699999999993,0.052300000000002456],[0,-30.667],[13.763800000000003,-6.038000000000011],[1,0],[0,45]],"o":[[8.1219,5.615299999999998],[6.427100000000003,4.218600000000002],[0,-6],[2.348399999999998,0.16949999999999932],[12.269999999999996,-2.485500000000002],[0,6],[-8.067499999999995,1.046599999999998],[-6.627600000000001,1.0523000000000025],[0,30.666700000000006],[-14.236199999999997,5.295999999999992],[-1,0],[0,-45],[0,0]],"v":[[17.5,28.5],[41.5,46],[62.5,53.5],[62.5,35.5],[69.5,36.5],[106.5,30.5],[106.5,48.5],[82.5,53],[62.5,54.5],[62.5,146.5],[20.5,163.5],[17.5,163.5],[17.5,28.5]]}}},{"ty":"fl","bm":0,"hd":false,"nm":"Fill","c":{"a":0,"k":[0.9412,0.9137,0.9137]},"r":2,"o":{"a":0,"k":100}},{"ty":"tr","a":{"a":0,"k":[0,0]},"s":{"a":0,"k":[100,100]},"sk":{"a":0,"k":0},"p":{"a":0,"k":[0,0]},"r":{"a":0,"k":0},"sa":{"a":0,"k":0},"o":{"a":0,"k":98.6}}]}],"ind":6},{"ty":4,"nm":"Shape Layer 7","sr":1,"st":0,"op":80,"ip":0,"hd":false,"ddd":0,"bm":0,"hasMask":false,"ao":0,"ks":{"a":{"a":0,"k":[0,0]},"s":{"a":0,"k":[100,100]},"sk":{"a":0,"k":0},"p":{"a":0,"k":[192.5,218]},"r":{"a":0,"k":0},"sa":{"a":0,"k":0},"o":{"a":0,"k":100}},"shapes":[{"ty":"gr","bm":0,"hd":false,"nm":"Group 7","it":[{"ty":"sh","bm":0,"hd":false,"nm":"Path 7","d":1,"ks":{"a":0,"k":{"c":true,"i":[[0,0],[10.711000000000013,-6.683300000000003],[4.070999999999998,-0.8562000000000012],[0.6670000000000016,0],[0,6],[-3.241000000000014,1.7886999999999986],[-8,6],[-3.4269999999999925,1.6289999999999996],[0.16599999999999682,-6.675000000000001]],"o":[[-9.955999999999989,7.649999999999999],[-3.929000000000002,1.4771],[-0.6670000000000016,0],[0,-6],[3.4259999999999877,-1.2113000000000014],[8,-6],[3.5730000000000075,-1.3710000000000004],[0.5,6.6583000000000006],[0,0]],"v":[[195.5,28.5],[164.5,50],[152.5,53.5],[150.5,53.5],[150.5,35.5],[160.5,31],[184.5,13],[195,8.5],[195.5,28.5]]}}},{"ty":"fl","bm":0,"hd":false,"nm":"Fill","c":{"a":0,"k":[0.9373,0.9098,0.9098]},"r":2,"o":{"a":0,"k":100}},{"ty":"tr","a":{"a":0,"k":[0,0]},"s":{"a":0,"k":[100,100]},"sk":{"a":0,"k":0},"p":{"a":0,"k":[0,0]},"r":{"a":0,"k":0},"sa":{"a":0,"k":0},"o":{"a":0,"k":99.2}}]}],"ind":7},{"ty":4,"nm":"Shape Layer 8","sr":1,"st":0,"op":80,"ip":0,"hd":false,"ddd":0,"bm":0,"hasMask":false,"ao":0,"ks":{"a":{"a":0,"k":[0,0]},"s":{"a":0,"k":[100,100]},"sk":{"a":0,"k":0},"p":{"a":0,"k":[192.5,218]},"r":{"a":0,"k":0},"sa":{"a":0,"k":0},"o":{"a":0,"k":100}},"shapes":[{"ty":"gr","bm":0,"hd":false,"nm":"Group 8","it":[{"ty":"sh","bm":0,"hd":false,"nm":"Path 8","d":1,"ks":{"a":0,"k":{"c":true,"i":[[0,0],[0,-6],[6.427100000000003,4.218600000000002],[8.1219,5.615299999999998],[-0.49960000000000093,6.6583000000000006],[-4.4544999999999995,-2.3109],[-7.1798,-5.090699999999998],[-3.4301999999999992,-1.213799999999999]],"o":[[0,6],[-7.572899999999997,-0.7813999999999979],[-7.878100000000003,-6.051400000000001],[-0.16629999999999967,-6.675000000000001],[4.5455000000000005,2.0223999999999993],[6.8202,5.575900000000001],[3.2364999999999995,1.786200000000001],[0,0]],"v":[[62.5,35.5],[62.5,53.5],[41.5,46],[17.5,28.5],[18,8.5],[31.5,15],[52.5,31],[62.5,35.5]]}}},{"ty":"fl","bm":0,"hd":false,"nm":"Fill","c":{"a":0,"k":[0.898,0.8667,0.8627]},"r":2,"o":{"a":0,"k":100}},{"ty":"tr","a":{"a":0,"k":[0,0]},"s":{"a":0,"k":[100,100]},"sk":{"a":0,"k":0},"p":{"a":0,"k":[0,0]},"r":{"a":0,"k":0},"sa":{"a":0,"k":0},"o":{"a":0,"k":99.2}}]}],"ind":8}]},{"nm":"Nested Scene 5_11","id":"precomp_newScene_0d500caa-2b2b-4b99-955c-65a99d72fcf4","fr":60,"layers":[{"ty":4,"nm":"Shape Layer - SVG","sr":1,"st":0,"op":135,"ip":0,"hd":false,"ln":"Layer_1","ddd":0,"bm":0,"hasMask":false,"ao":0,"ks":{"a":{"a":0,"k":[262,262]},"s":{"a":0,"k":[100,100]},"sk":{"a":0,"k":0},"p":{"a":0,"k":[301,301]},"r":{"a":0,"k":0},"sa":{"a":0,"k":0},"o":{"a":0,"k":100}},"shapes":[{"ty":"gr","bm":0,"hd":false,"nm":"Group 1","it":[{"ty":"sh","bm":0,"hd":false,"nm":"Path 1","d":1,"ks":{"a":0,"k":{"c":true,"i":[[0,0],[-7.681548999999961,-2.1246650000000216],[1.3395080000000235,-9.813979999999987],[2.5446779999999762,-3.8908389999999997],[3.8107909999999947,-5.56045499999999],[0.041442999999958374,-2.0391090000000247],[-0.33184899999997697,-8.653885000000002],[8.903687000000048,3.9382630000000063],[5.963898000000029,2.3186039999999934],[6.933411000000007,-2.920242000000002],[6.3461309999999855,-1.6913749999999936],[0.03276100000002202,11.745711999999997],[-0.6356200000000172,6.7736659999999915],[3.8968500000000006,5.065628000000004],[3.7754209999999944,4.782730000000015],[-10.322662000000008,4.440674000000001],[-5.91360499999999,1.3123020000000167],[-4.844376000000011,8.496566999999999],[-3.1595769999999845,3.538162],[-6.608734000000027,-8.656432999999993],[-3.1013489999999706,-4.2452399999999955],[-2.729949999999974,-3.340851000000015]],"o":[[7.804290999999978,2.9010920000000056],[10.894806000000017,3.0134280000000047],[-0.6008609999999521,4.402145000000019],[-3.6854850000000283,5.635146999999989],[-1.1209410000000162,1.6355289999999911],[-0.17608699999999544,8.663023999999979],[0.38568099999997685,10.05702199999996],[-5.834380999999951,-2.580658000000028],[-7.036377000000016,-2.7355340000000012],[-6.049316000000005,2.5478519999999776],[-7.877944000000014,2.099640000000022],[-0.01907299999999168,-6.833236999999997],[0.6449580000000026,-6.873032000000023],[-3.715102999999999,-4.829361000000006],[-6.350509999999986,-8.044844999999981],[5.540344000000005,-2.3833930000000123],[10.040527000000026,-2.228149000000002],[2.3499300000000005,-4.121551000000011],[7.519607000000036,-8.420569999999998],[3.187866999999983,4.175629000000015],[2.327393000000029,3.1858210000000042],[0,0]],"v":[[292.330444,158.831299],[315.236725,166.925812],[331.724274,187.084656],[325.673492,199.664017],[313.727295,215.990387],[312.072693,222.017838],[312.066956,248.013504],[289.782318,264.134857],[271.657898,257.791107],[251.027679,258.354126],[232.336349,264.676849],[212.006027,247.52327],[212.141556,227.036423],[206.231415,209.790558],[194.944931,195.411163],[202.739105,169.220032],[220.167557,163.983917],[241.159836,146.716476],[249.495041,135.10495],[275.662048,136.369293],[284.701843,149.296967],[292.330444,158.831299]]}}},{"ty":"fl","bm":0,"hd":false,"nm":"Fill","c":{"a":0,"k":[0.902,0.6275,0.3529]},"r":1,"o":{"a":0,"k":100}},{"ty":"tr","a":{"a":0,"k":[0,0]},"s":{"a":0,"k":[100,100]},"sk":{"a":0,"k":0},"p":{"a":0,"k":[0,0]},"r":{"a":0,"k":0},"sa":{"a":0,"k":0},"o":{"a":0,"k":100}}]},{"ty":"gr","bm":0,"hd":false,"nm":"Group 2","it":[{"ty":"sh","bm":0,"hd":false,"nm":"Path 2","d":1,"ks":{"a":0,"k":{"c":false,"i":[[0,0],[1.3618620000000021,12.526320999999996],[-6.238281000000001,17.467284999999976],[-17.19717399999999,14.103622000000001],[-20.221374999999995,3.99427],[-18.07052600000003,-4.8082430000000045],[-16.46963500000004,-18.76689900000001],[-4.25546300000002,-20.047195999999985],[17.786103000000026,-28.81565900000001],[23.020172000000002,-9.996032000000014],[12.727355999999986,-1.4107359999999858],[22.358261,11.90072600000002],[10.946578999999986,19.64681999999999],[2.650558999999987,5.3242489999999805]],"o":[[-5.003447999999992,-11.923202000000003],[-2.043853999999982,-18.799117999999993],[7.485458999999992,-20.95944300000002],[16.085876000000013,-13.192222999999998],[18.358002,-3.6261909999999915],[24.25253299999997,6.453147999999999],[13.552641999999992,15.443047000000007],[6.986847000000012,32.914444],[-13.342955999999958,21.61721799999998],[-11.543213000000037,5.012420999999961],[-25.6353,2.8414619999999786],[-19.685485999999997,-10.478088000000014],[-2.701385000000016,-4.848388999999997],[0,0]],"v":[[148.698654,244.349533],[139.793976,207.886551],[147.053436,153.721436],[184.764252,101.572403],[239.453644,76.325745],[294.136932,78.55896],[355.114838,116.701637],[381.858948,170.196732],[365.8078,262.818329],[310.919006,309.873077],[274.456543,319.2117],[202.662094,304.762268],[156.296997,259.624054],[148.698654,244.349533]]}}},{"ty":"sh","bm":0,"hd":false,"nm":"Path 3","d":1,"ks":{"a":0,"k":{"c":true,"i":[[0,0],[2.327393000000029,3.1858210000000042],[3.187866999999983,4.175629000000015],[7.519607000000036,-8.420569999999998],[2.3499300000000005,-4.121551000000011],[10.040527000000026,-2.228149000000002],[5.540344000000005,-2.3833930000000123],[-6.350509999999986,-8.044844999999981],[-3.715102999999999,-4.829361000000006],[0.6449580000000026,-6.873032000000023],[-0.01907299999999168,-6.833236999999997],[-7.877944000000014,2.099640000000022],[-6.049316000000005,2.5478519999999776],[-7.036377000000016,-2.7355340000000012],[-5.834380999999951,-2.580658000000028],[0.38568099999997685,10.05702199999996],[-0.17608699999999544,8.663023999999979],[-1.1209410000000162,1.6355289999999911],[-3.6854850000000283,5.635146999999989],[-0.6008609999999521,4.402145000000019],[10.894806000000017,3.0134280000000047],[8.071594000000005,3.154953000000006]],"o":[[-2.462646999999947,-3.0869900000000143],[-3.1013489999999706,-4.2452399999999955],[-6.608734000000027,-8.656432999999993],[-3.1595769999999845,3.538162],[-4.844376000000011,8.496566999999999],[-5.91360499999999,1.3123020000000167],[-10.322662000000008,4.440674000000001],[3.7754209999999944,4.782730000000015],[3.8968500000000006,5.065628000000004],[-0.6356200000000172,6.7736659999999915],[0.03276100000002202,11.745711999999997],[6.3461309999999855,-1.6913749999999936],[6.933411000000007,-2.920242000000002],[5.963898000000029,2.3186039999999934],[8.903687000000048,3.9382630000000063],[-0.33184899999997697,-8.653885000000002],[0.041442999999958374,-2.0391090000000247],[3.8107909999999947,-5.56045499999999],[2.5446779999999762,-3.8908389999999997],[1.3395080000000235,-9.813979999999987],[-7.681548999999961,-2.1246650000000216],[0,0]],"v":[[292.063141,158.577438],[284.701843,149.296967],[275.662048,136.369293],[249.495041,135.10495],[241.159836,146.716476],[220.167557,163.983917],[202.739105,169.220032],[194.944931,195.411163],[206.231415,209.790558],[212.141556,227.036423],[212.006027,247.52327],[232.336349,264.676849],[251.027679,258.354126],[271.657898,257.791107],[289.782318,264.134857],[312.066956,248.013504],[312.072693,222.017838],[313.727295,215.990387],[325.673492,199.664017],[331.724274,187.084656],[315.236725,166.925812],[292.063141,158.577438]]}}},{"ty":"fl","bm":0,"hd":false,"nm":"Fill","c":{"a":0,"k":[0.9686,0.9608,0.9608]},"r":1,"o":{"a":0,"k":100}},{"ty":"tr","a":{"a":0,"k":[0,0]},"s":{"a":0,"k":[100,100]},"sk":{"a":0,"k":0},"p":{"a":0,"k":[0,0]},"r":{"a":0,"k":0},"sa":{"a":0,"k":0},"o":{"a":0,"k":100}}]},{"ty":"gr","bm":0,"hd":false,"nm":"Group 3","it":[{"ty":"sh","bm":0,"hd":false,"nm":"Path 4","d":1,"ks":{"a":0,"k":{"c":true,"i":[[0,0],[-0.0036320000000387154,-6.7738030000000435],[0.00814900000000307,-0.2427059999999983],[12.954834000000005,2.631621999999993],[1.7374879999999848,0.1469109999999887],[0.011992999999961285,6.76074200000005],[-8.762329000000022,-1.0870660000000498],[-6.104981000000009,-0.22003200000000334]],"o":[[0.41583200000002307,6.363189000000034],[0.008055999999953656,0.47033699999997225],[-13.469786999999997,1.1932369999999537],[-1.2893669999999702,-0.2619329999999991],[-0.4296269999999822,-6.308167000000026],[8.708800999999994,1.0108640000000264],[5.618163999999979,0.6970219999999472],[0,0]],"v":[[305.600037,388.107178],[306.015076,407.547607],[305.997192,408.746277],[266.795013,403.442963],[262.433716,402.994141],[261.986481,383.621002],[288.138031,387.465881],[305.600037,388.107178]]}}},{"ty":"fl","bm":0,"hd":false,"nm":"Fill","c":{"a":0,"k":[0.898,0.8667,0.8627]},"r":1,"o":{"a":0,"k":100}},{"ty":"tr","a":{"a":0,"k":[0,0]},"s":{"a":0,"k":[100,100]},"sk":{"a":0,"k":0},"p":{"a":0,"k":[0,0]},"r":{"a":0,"k":0},"sa":{"a":0,"k":0},"o":{"a":0,"k":100}}]},{"ty":"gr","bm":0,"hd":false,"nm":"Group 4","it":[{"ty":"sh","bm":0,"hd":false,"nm":"Path 5","d":1,"ks":{"a":0,"k":{"c":false,"i":[[0,0],[18.013458000000014,-9.031371999999976],[15.571716000000038,-2.1315309999999954],[9.075317999999982,0.04547100000002047],[26.384994000000006,19.40600599999999],[9.086365,35.81187399999999],[-0.9562759999999884,14.803923999999995],[-22.813027000000005,26.847099],[-34.32690400000001,7.374409],[-29.22473199999996,-11.899700000000003],[-15.504517000000021,-17.044776999999996],[-4.753112999999985,-29.556579999999997],[26.82702599999999,-35.948578],[1.696532999999988,-2.067108000000019]],"o":[[-13.787476000000026,15.138184000000024],[-13.980346999999995,7.009307999999976],[-9.001739999999984,1.2322389999999928],[-32.90023800000003,-0.1646729999999934],[-29.691757999999993,-21.838134000000025],[-3.64430999999999,-14.36322100000001],[2.2446060000000045,-34.74818399999998],[22.918334999999985,-26.971024],[30.781997999999987,-6.6128730000000004],[21.46844500000003,8.741507999999996],[20.153412000000003,22.155518],[7.139861999999994,44.39842200000001],[-1.3867190000000278,1.8582150000000297],[0,0]],"v":[[378.766541,297.713867],[331.603577,334.538544],[287.295441,348.892792],[260.073364,350.892548],[170.921021,321.163116],[112.695709,234.384995],[108.083801,190.535126],[144.565674,97.790062],[230.570694,46.419235],[320.713959,54.844498],[376.121399,93.746147],[413.809052,171.526413],[383.359528,292.022156],[378.766541,297.713867]]}}},{"ty":"sh","bm":0,"hd":false,"nm":"Path 6","d":1,"ks":{"a":0,"k":{"c":true,"i":[[0,0],[-2.701385000000016,-4.848388999999997],[-19.685485999999997,-10.478088000000014],[-25.6353,2.8414619999999786],[-11.543213000000037,5.012420999999961],[-13.342955999999958,21.61721799999998],[6.986847000000012,32.914444],[13.552641999999992,15.443047000000007],[24.25253299999997,6.453147999999999],[18.358002,-3.6261909999999915],[16.085876000000013,-13.192222999999998],[7.485458999999992,-20.95944300000002],[-2.043853999999982,-18.799117999999993],[-5.198454999999996,-12.262100000000004]],"o":[[2.455551999999983,4.98535099999998],[10.946578999999986,19.64681999999999],[22.358261,11.90072600000002],[12.727355999999986,-1.4107359999999858],[23.020172000000002,-9.996032000000014],[17.786103000000026,-28.81565900000001],[-4.25546300000002,-20.047195999999985],[-16.46963500000004,-18.76689900000001],[-18.07052600000003,-4.8082430000000045],[-20.221374999999995,3.99427],[-17.19717399999999,14.103622000000001],[-6.238281000000001,17.467284999999976],[1.3618620000000021,12.526320999999996],[0,0]],"v":[[148.893661,244.688431],[156.296997,259.624054],[202.662094,304.762268],[274.456543,319.2117],[310.919006,309.873077],[365.8078,262.818329],[381.858948,170.196732],[355.114838,116.701637],[294.136932,78.55896],[239.453644,76.325745],[184.764252,101.572403],[147.053436,153.721436],[139.793976,207.886551],[148.893661,244.688431]]}}},{"ty":"fl","bm":0,"hd":false,"nm":"Fill","c":{"a":0,"k":[0.8,0.5255,0.2471]},"r":1,"o":{"a":0,"k":100}},{"ty":"tr","a":{"a":0,"k":[0,0]},"s":{"a":0,"k":[100,100]},"sk":{"a":0,"k":0},"p":{"a":0,"k":[0,0]},"r":{"a":0,"k":0},"sa":{"a":0,"k":0},"o":{"a":0,"k":100}}]},{"ty":"gr","bm":0,"hd":false,"nm":"Group 5","it":[{"ty":"sh","bm":0,"hd":false,"nm":"Path 7","d":1,"ks":{"a":0,"k":{"c":true,"i":[[0,0],[-0.22106899999999996,-5.131867],[3.774107999999984,1.1613460000000373],[8.238372999999996,6.509703999999999],[4.255538999999999,2.6839899999999943],[-0.026961999999997488,7.484161000000029],[-6.8484499999999855,-4.821655000000021],[-7.764952999999991,-4.883940999999993]],"o":[[0.35465999999999553,5.219940000000008],[0.19413800000000947,4.506713999999988],[-10.156678,-3.125304999999969],[-3.7037660000000017,-2.926544999999976],[-0.40393000000000256,-7.022155999999995],[8.687881000000004,0.9130550000000426],[7.211943999999988,5.0776369999999815],[0,0]],"v":[[217.656677,388.08197],[218.050308,403.583008],[212.578278,407.372467],[185.527176,392.1008],[173.509918,384.011963],[173.087311,362.485779],[195.127747,373.525818],[217.656677,388.08197]]}}},{"ty":"fl","bm":0,"hd":false,"nm":"Fill","c":{"a":0,"k":[0.898,0.8667,0.8627]},"r":1,"o":{"a":0,"k":100}},{"ty":"tr","a":{"a":0,"k":[0,0]},"s":{"a":0,"k":[100,100]},"sk":{"a":0,"k":0},"p":{"a":0,"k":[0,0]},"r":{"a":0,"k":0},"sa":{"a":0,"k":0},"o":{"a":0,"k":100}}]},{"ty":"gr","bm":0,"hd":false,"nm":"Group 6","it":[{"ty":"sh","bm":0,"hd":false,"nm":"Path 8","d":1,"ks":{"a":0,"k":{"c":true,"i":[[0,0],[3.8588249999999675,-2.9252930000000106],[10.416015999999956,-2.5399469999999837],[2.039001999999982,0.20156900000000633],[-0.004424999999969259,6.303496999999993],[-8.804809000000034,5.303069999999991],[-6.411804000000018,3.1616820000000416],[0.023894999999981792,-7.482452000000023]],"o":[[-4.157807000000048,3.094695999999999],[-8.314910999999995,6.3034359999999765],[-1.5869140000000357,0.3869629999999802],[-0.4178770000000327,-6.7698970000000145],[8.655426000000034,-5.551117000000033],[5.825896999999998,-3.5088499999999954],[0.432158999999956,7.024414000000036],[0,0]],"v":[[350.922272,383.543518],[338.639069,391.950897],[311.697601,407.198486],[306.429321,407.543701],[306.020294,388.16687],[332.025543,371.578186],[350.461853,362.017639],[350.922272,383.543518]]}}},{"ty":"fl","bm":0,"hd":false,"nm":"Fill","c":{"a":0,"k":[0.9412,0.9137,0.9137]},"r":1,"o":{"a":0,"k":100}},{"ty":"tr","a":{"a":0,"k":[0,0]},"s":{"a":0,"k":[100,100]},"sk":{"a":0,"k":0},"p":{"a":0,"k":[0,0]},"r":{"a":0,"k":0},"sa":{"a":0,"k":0},"o":{"a":0,"k":100}}]},{"ty":"gr","bm":0,"hd":false,"nm":"Group 7","it":[{"ty":"sh","bm":0,"hd":false,"nm":"Path 9","d":1,"ks":{"a":0,"k":{"c":true,"i":[[0,0],[-0.00009099999999762076,-38.42691000000002],[5.612853999999999,2.22235100000006],[9.066115999999994,3.7418520000000512],[0.20034700000002204,28.786651000000006],[-4.302245999999997,0.3088989999999967],[-8.313750999999996,1.2929690000000278],[-4.642853000000002,0.7691340000000082]],"o":[[0.4208980000000224,37.971069],[-5.722960999999998,-1.4924919999999702],[-8.766402999999997,-3.4710079999999834],[-0.37870799999998894,-28.86651599999999],[-0.030883999999986145,-4.437713999999971],[8.36900399999999,-0.6009519999999497],[4.2419280000000015,-0.6597289999999703],[0,0]],"v":[[261.57074,403.008698],[261.994354,517.375488],[244.850632,511.930908],[218.38385,500.91333],[217.898148,414.471497],[223.493301,408.816742],[248.475708,405.301117],[261.57074,403.008698]]}}},{"ty":"fl","bm":0,"hd":false,"nm":"Fill","c":{"a":0,"k":[0.9686,0.9608,0.9608]},"r":1,"o":{"a":0,"k":100}},{"ty":"tr","a":{"a":0,"k":[0,0]},"s":{"a":0,"k":[100,100]},"sk":{"a":0,"k":0},"p":{"a":0,"k":[0,0]},"r":{"a":0,"k":0},"sa":{"a":0,"k":0},"o":{"a":0,"k":100}}]},{"ty":"gr","bm":0,"hd":false,"nm":"Group 8","it":[{"ty":"sh","bm":0,"hd":false,"nm":"Path 10","d":1,"ks":{"a":0,"k":{"c":true,"i":[[0,0],[-0.007447000000013304,-30.76721200000003],[13.781524999999988,-5.6043090000000575],[1.028839000000005,0.4448849999999993],[0.002624000000025717,37.96878099999998],[-0.42904699999996865,0.00119000000000824],[-1.2893669999999702,-0.2619329999999991],[-13.46160900000001,0.9504999999999768]],"o":[[0.004944000000023152,30.309204000000022],[-13.769196000000022,6.086365000000001],[-0.5796809999999937,0.23577799999998206],[-0.3922120000000291,-38.50320399999998],[0,0],[1.7426150000000007,0.14178400000002966],[12.954834000000005,2.631621999999993],[0,0]],"v":[[305.989014,408.989014],[306.006348,500.374634],[264.686096,517.699097],[262.386475,517.451782],[261.989014,403.010986],[262.428589,402.999268],[266.795013,403.442963],[305.989014,408.989014]]}}},{"ty":"fl","bm":0,"hd":false,"nm":"Fill","c":{"a":0,"k":[0.9412,0.9137,0.9137]},"r":1,"o":{"a":0,"k":100}},{"ty":"tr","a":{"a":0,"k":[0,0]},"s":{"a":0,"k":[100,100]},"sk":{"a":0,"k":0},"p":{"a":0,"k":[0,0]},"r":{"a":0,"k":0},"sa":{"a":0,"k":0},"o":{"a":0,"k":100}}]},{"ty":"gr","bm":0,"hd":false,"nm":"Group 9","it":[{"ty":"sh","bm":0,"hd":false,"nm":"Path 11","d":1,"ks":{"a":0,"k":{"c":true,"i":[[0,0],[-0.03283700000002909,-44.14633199999997],[0.27621500000003607,-1.1795039999999517],[14.902405000000044,6.370421999999962],[-0.003233999999963544,30.551941],[-0.4142460000000483,0.0039059999999722095],[-1.5869140000000357,0.3869629999999802],[-8.314910999999995,6.3034359999999765],[-4.081757000000039,2.631194999999991]],"o":[[0.04745500000001357,44.14633199999997],[0.00033499999995001417,0.46588100000008126],[-14.685485999999969,-5.899962999999957],[-0.3889159999999947,-30.846802000000025],[0.00814900000000307,-0.2427059999999983],[2.0309449999999742,-0.26876800000002277],[10.416015999999956,-2.5399469999999837],[3.8588249999999675,-2.9252930000000106],[0,0]],"v":[[350.846222,384.007019],[350.974976,516.445984],[350.49411,518.557434],[306.387817,500.454224],[305.997192,408.746277],[306.437378,408.014038],[311.697601,407.198486],[338.639069,391.950897],[350.846222,384.007019]]}}},{"ty":"fl","bm":0,"hd":false,"nm":"Fill","c":{"a":0,"k":[0.9686,0.9608,0.9608]},"r":1,"o":{"a":0,"k":100}},{"ty":"tr","a":{"a":0,"k":[0,0]},"s":{"a":0,"k":[100,100]},"sk":{"a":0,"k":0},"p":{"a":0,"k":[0,0]},"r":{"a":0,"k":0},"sa":{"a":0,"k":0},"o":{"a":0,"k":100}}]},{"ty":"gr","bm":0,"hd":false,"nm":"Group 10","it":[{"ty":"sh","bm":0,"hd":false,"nm":"Path 12","d":1,"ks":{"a":0,"k":{"c":true,"i":[[0,0],[-12.247176999999994,1.4501339999999914],[-2.566071000000022,-0.3235779999999977],[-0.0005499999999756255,-6.309387000000015],[0.4182739999999967,0.002288000000021384],[4.2419280000000015,-0.6597289999999703],[8.36900399999999,-0.6009519999999497],[-0.030883999999986145,-4.437713999999971],[-0.002853999999985035,-28.788025000000005],[15.60270700000001,-6.205566999999974],[-0.42753600000000347,44.77835099999999],[-3.7037660000000017,-2.926544999999976],[-10.156678,-3.125304999999969],[0.19413800000000947,4.506713999999988],[-0.006866999999999734,5.141661999999997]],"o":[[12.769058000000001,2.776397999999972],[2.116913000000011,-0.2506410000000301],[0.4484249999999861,6.824615000000051],[-0.005096999999977925,0.005096999999977925],[-4.642853000000002,0.7691340000000082],[-8.313750999999996,1.2929690000000278],[-4.302245999999997,0.3088989999999967],[0.20034700000002204,28.786651000000006],[-14.696076000000005,5.844910000000027],[0,-45.159362999999985],[4.324768000000006,2.2204889999999864],[8.238372999999996,6.509703999999999],[3.774107999999984,1.1613460000000373],[-0.22106899999999996,-5.131867],[0,0]],"v":[[218.018204,388.160248],[254.738312,383.634674],[261.550049,383.557129],[262.004639,402.995361],[261.57074,403.008698],[248.475708,405.301117],[223.493301,408.816742],[217.898148,414.471497],[218.007996,500.834839],[173.013153,518.730286],[173.440689,384.475464],[185.527176,392.1008],[212.578278,407.372467],[218.050308,403.583008],[218.018204,388.160248]]}}},{"ty":"fl","bm":0,"hd":false,"nm":"Fill","c":{"a":0,"k":[0.9412,0.9137,0.9137]},"r":1,"o":{"a":0,"k":100}},{"ty":"tr","a":{"a":0,"k":[0,0]},"s":{"a":0,"k":[100,100]},"sk":{"a":0,"k":0},"p":{"a":0,"k":[0,0]},"r":{"a":0,"k":0},"sa":{"a":0,"k":0},"o":{"a":0,"k":100}}]},{"ty":"gr","bm":0,"hd":false,"nm":"Group 11","it":[{"ty":"sh","bm":0,"hd":false,"nm":"Path 13","d":1,"ks":{"a":0,"k":{"c":true,"i":[[0,0],[2.289778999999996,-4.9093170000000015],[2.1951679999999953,-20.015029999999996],[-6.366188000000008,-22.871490000000023],[-15.855796999999995,-20.09768600000001],[-32.98635899999999,-12.393767999999966],[-18.199036000000007,-1.315307999999959],[-24.229827999999998,8.197997999999984],[-16.099304000000018,12.295501999999999],[-2.350036999999986,1.1364750000000186],[4.345673000000033,-6.188658999999973],[9.765990999999985,-2.480743000000018],[4.220704000000012,-1.1151429999999891],[5.825896999999998,-3.5088499999999954],[9.075683000000026,-5.491394000000014],[5.618163999999979,0.6970219999999472],[9.151581000000022,1.5312190000000214],[2.116913000000011,-0.2506410000000301],[13.130584999999996,2.8546759999999836],[7.211943999999988,5.0776369999999815],[8.615309999999994,1.3773500000000354],[7.056397000000004,1.5450739999999996],[5.184570000000008,9.45126399999998],[2.628655000000009,5.400267999999983],[7.485427999999999,5.674133999999981],[2.4375769999999903,10.35153200000002],[-0.3119959999999935,5.486725000000035],[7.298714000000004,13.231003000000015],[0.37630400000000463,6.574204000000009],[-2.0576779999999957,6.103104000000002],[-1.957451000000006,5.841858000000002],[-0.6760249999999957,6.0809019999999805],[-0.06252299999999877,7.592520999999991],[-7.750694999999993,7.281639999999996],[-3.98156800000001,2.818091999999993]],"o":[[-1.7692650000000043,4.931708999999998],[-8.575980999999999,18.38703199999999],[-2.592049000000003,23.633712000000003],[6.857367999999994,24.63606299999998],[22.007553,27.895263999999997],[16.933441000000016,6.362304999999992],[25.76559400000002,1.8621219999999994],[19.194732999999985,-6.494354000000044],[1.7988579999999956,-1.3738399999999729],[-3.3672490000000153,6.60873399999997],[-6.2732540000000085,8.933686000000023],[-3.5987850000000208,0.9141239999999584],[-6.619017999999983,3.5045470000000023],[-8.804809000000034,5.303069999999991],[-6.104981000000009,-0.22000100000002476],[-8.762329000000022,-1.0870660000000498],[-2.5597230000000195,0.13290399999999636],[-12.247176999999994,1.4501339999999914],[-7.764952999999991,-4.883940999999993],[-6.8484499999999855,-4.821655000000021],[-6.962052,-1.9759520000000066],[-11.34994500000002,-2.4852599999999825],[-2.886718999999985,-5.262390000000039],[-4.250816,-8.732819000000006],[-8.040237000000005,-6.09466500000002],[-1.2642740000000003,-5.3689580000000205],[0.8553850000000125,-15.042648999999983],[-3.226692,-5.849303999999989],[-0.35546099999999115,-6.209854000000007],[1.9687650000000048,-5.839401000000009],[1.941040000000001,-5.792877000000004],[0.8374790000000019,-7.533294000000012],[0.10063999999999851,-12.223893000000004],[3.3072050000000104,-3.107048000000006],[0,0]],"v":[[110.586678,87.937447],[104.555672,102.836021],[89.111557,160.715363],[95.381432,230.569351],[129.824173,297.438934],[212.839081,357.243835],[265.647583,368.19458],[340.398285,357.977051],[393.170502,329.397247],[399.478516,325.984802],[388.541656,345.758514],[362.151001,358.982208],[350.669067,361.674774],[332.025543,371.578186],[305.600037,388.107147],[288.138031,387.465881],[261.543701,383.100647],[254.738312,383.634674],[217.656677,388.08197],[195.127747,373.525818],[173.159882,362.021484],[152.25621,356.173584],[129.160385,336.433685],[121.070686,320.33429],[102.065033,300.03186],[83.774246,277.175232],[82.124603,260.604523],[72.459251,218.560104],[66.380997,199.21553],[70.445076,180.347],[77.99675,163.38385],[81.866005,145.378082],[82.912544,122.620232],[99.393639,96.334106],[110.586678,87.937447]]}}},{"ty":"fl","bm":0,"hd":false,"nm":"Fill","c":{"a":0,"k":[0.8,0.5255,0.2471]},"r":1,"o":{"a":0,"k":100}},{"ty":"tr","a":{"a":0,"k":[0,0]},"s":{"a":0,"k":[100,100]},"sk":{"a":0,"k":0},"p":{"a":0,"k":[0,0]},"r":{"a":0,"k":0},"sa":{"a":0,"k":0},"o":{"a":0,"k":100}}]},{"ty":"gr","bm":0,"hd":false,"nm":"Group 12","it":[{"ty":"sh","bm":0,"hd":false,"nm":"Path 14","d":1,"ks":{"a":0,"k":{"c":false,"i":[[0,0],[-3.8987199999999973,10.131890000000006],[-16.072647999999987,2.4616780000000063],[-9.757843000000008,8.524847000000001],[-3.760101999999989,2.567832000000001],[-10.82611,-1.8334489999999999],[-8.880370999999968,-0.0009499999999995623],[-7.468504999999993,1.593703999999999],[-9.879119000000003,-8.130079],[-11.380461999999966,-3.0254499999999993],[-5.88284299999998,-0.9483490000000003],[-6.058929999999975,-11.243576000000004],[-2.5396120000000337,-5.423134000000005],[-7.34027100000003,-5.775238999999999],[-2.6459350000000086,-10.314575000000005],[0.20001200000001518,-3.6522899999999936],[-9.262360000000001,-14.853545999999994],[-1.1942750000000046,-2.4688569999999856],[5.620392000000038,-10.039580999999998],[-0.7295530000000099,-16.77188099999998],[6.486634000000038,-6.515502999999967],[4.8158880000000295,-3.8366399999999885],[5.145873999999992,-10.416717000000006],[1.7988579999999956,-1.3738399999999729],[19.194732999999985,-6.494354000000044],[25.76559400000002,1.8621219999999994],[16.933441000000016,6.362304999999992],[22.007553,27.895263999999997],[6.857367999999994,24.63606299999998],[-2.592049000000003,23.633712000000003],[-8.575980999999999,18.38703199999999],[-2.1178740000000005,4.989486999999997]],"o":[[7.3779150000000016,-7.975235000000012],[6.199737999999996,-16.111750999999998],[12.904129000000012,-1.9763829999999984],[3.419205000000005,-2.9871739999999996],[9.793655000000001,-6.688261999999999],[8.828537000000011,1.4951519999999991],[7.519745,0.0008049999999997226],[12.25726400000002,-2.615583],[8.73431400000004,7.187957000000001],[5.7870490000000245,1.5384559999999965],[13.392303000000027,2.158928000000003],[2.8403620000000274,5.270793999999995],[4.145629999999983,8.852677],[7.905944999999974,6.220305999999994],[0.9238279999999577,3.601264999999998],[-0.930451000000005,16.987488000000013],[1.430878000000007,2.2946170000000166],[5.554473999999971,11.482392000000004],[-8.345794999999953,14.907882999999998],[0.3692320000000109,8.488312000000008],[-4.35159299999998,4.371002000000033],[-8.58068800000001,6.835937000000001],[-2.426269999999988,1.494324000000006],[-16.099304000000018,12.295501999999999],[-24.229827999999998,8.197997999999984],[-18.199036000000007,-1.315307999999959],[-32.98635899999999,-12.393767999999966],[-15.855796999999995,-20.09768600000001],[-6.366188000000008,-22.871490000000023],[2.1951679999999953,-20.015029999999996],[2.289778999999996,-4.9093170000000015],[0,0]],"v":[[110.935287,87.879669],[127.75296,60.668472],[162.936768,35.038681],[196.625259,18.958378],[207.607056,10.830521],[238.901199,7.356681],[265.531433,10.709519],[288.081573,6.88564],[321.121429,14.488129],[349.801025,32.362648],[367.182892,36.861095],[394.895691,58.629707],[402.92984,74.702667],[421.971649,94.952538],[440.268341,117.791656],[441.901276,128.852905],[451.942749,177.006973],[455.040497,184.639816],[452.071808,217.253601],[441.852661,264.558929],[434.33905,288.157898],[420.711029,300.687317],[399.554749,325.626953],[393.170502,329.397247],[340.398285,357.977051],[265.647583,368.19458],[212.839081,357.243835],[129.824173,297.438934],[95.381432,230.569351],[89.111557,160.715363],[104.555672,102.836021],[110.935287,87.879669]]}}},{"ty":"sh","bm":0,"hd":false,"nm":"Path 15","d":1,"ks":{"a":0,"k":{"c":true,"i":[[0,0],[-1.3867190000000278,1.8582150000000297],[7.139861999999994,44.39842200000001],[20.153412000000003,22.155518],[21.46844500000003,8.741507999999996],[30.781997999999987,-6.6128730000000004],[22.918334999999985,-26.971024],[2.2446060000000045,-34.74818399999998],[-3.64430999999999,-14.36322100000001],[-29.691757999999993,-21.838134000000025],[-32.90023800000003,-0.1646729999999934],[-9.001739999999984,1.2322389999999928],[-13.980346999999995,7.009307999999976],[-14.031555000000026,15.396149000000037]],"o":[[1.4524539999999888,-1.809143000000006],[26.82702599999999,-35.948578],[-4.753112999999985,-29.556579999999997],[-15.504517000000021,-17.044776999999996],[-29.22473199999996,-11.899700000000003],[-34.32690400000001,7.374409],[-22.813027000000005,26.847099],[-0.9562759999999884,14.803923999999995],[9.086365,35.81187399999999],[26.384994000000006,19.40600599999999],[9.075317999999982,0.04547100000002047],[15.571716000000038,-2.1315309999999954],[18.013458000000014,-9.031371999999976],[0,0]],"v":[[379.01062,297.455902],[383.359528,292.022156],[413.809052,171.526413],[376.121399,93.746147],[320.713959,54.844498],[230.570694,46.419235],[144.565674,97.790062],[108.083801,190.535126],[112.695709,234.384995],[170.921021,321.163116],[260.073364,350.892548],[287.295441,348.892792],[331.603577,334.538544],[379.01062,297.455902]]}}},{"ty":"fl","bm":0,"hd":false,"nm":"Fill","c":{"a":0,"k":[0.902,0.6275,0.3529]},"r":1,"o":{"a":0,"k":100}},{"ty":"tr","a":{"a":0,"k":[0,0]},"s":{"a":0,"k":[100,100]},"sk":{"a":0,"k":0},"p":{"a":0,"k":[0,0]},"r":{"a":0,"k":0},"sa":{"a":0,"k":0},"o":{"a":0,"k":100}}]}],"ind":1}]},{"nm":"Nested Scene 5_12","id":"precomp_newScene_fe949ba2-b608-4192-8084-c05f156f3270","fr":60,"layers":[{"ty":4,"nm":"Shape Layer - SVG","sr":1,"st":0,"op":135,"ip":0,"hd":false,"ln":"Layer_1","ddd":0,"bm":0,"hasMask":false,"ao":0,"ks":{"a":{"a":0,"k":[201.5,197.5]},"s":{"a":0,"k":[100,100]},"sk":{"a":0,"k":0},"p":{"a":0,"k":[301,301]},"r":{"a":0,"k":0},"sa":{"a":0,"k":0},"o":{"a":0,"k":100}},"shapes":[{"ty":"gr","bm":0,"hd":false,"nm":"Group 1","it":[{"ty":"sh","bm":0,"hd":false,"nm":"Path 1","d":1,"ks":{"a":0,"k":{"c":true,"i":[[0,0],[-2.4191590000000076,-4.839783000000011],[-8.53422599999999,-2.2629540000000077],[-5.173430999999994,-3.0083159999999793],[7.163482999999985,-8.953842000000009],[3.697022000000004,-4.6846769999999935],[-0.29995700000000625,-5.155869000000024],[0.07421899999999937,-7.15879799999999],[12.102875000000012,3.9043889999999806],[6.912338000000005,1.560608000000002],[4.49588,-1.0444329999999695],[6.303406000000024,-2.068877999999984],[0.35572799999999916,13.215285999999992],[0.3287809999999922,7.978577000000001],[1.5285800000000052,2.3184510000000103],[4.326355000000007,5.4540250000000015],[-13.832840000000004,2.9783789999999897],[-6.857224000000002,2.807220000000001],[-2.1273350000000164,2.8409730000000195],[-4.034179999999992,5.46577400000001],[-7.463364000000013,-10.012816999999998]],"o":[[3.31347599999998,4.791489000000013],[4.385528999999991,8.773818000000006],[5.859526999999986,1.5537269999999808],[9.92764299999999,5.772887999999995],[-3.727661000000012,4.659255999999999],[-3.1153100000000222,3.947525000000013],[0.4151149999999859,7.135405999999989],[-0.13186600000000226,12.72224399999999],[-6.786284999999992,-2.189270000000022],[-4.462707999999992,-1.007567999999992],[-6.42437799999999,1.492432000000008],[-12.453460999999976,4.087432999999976],[-0.21498099999999454,-7.9863129999999956],[-0.11558600000000752,-2.805251999999996],[-3.8267060000000015,-5.804092999999995],[-8.845756000000009,-11.151381999999984],[7.260955999999993,-1.5633700000000204],[3.0496980000000065,-1.2484890000000064],[4.070754999999991,-5.436249000000004],[7.208159999999992,-9.766097999999985],[0,0]],"v":[[216.357819,136.609344],[225.782745,150.444016],[246.529099,164.101379],[263.634277,170.348267],[267.978027,197.512009],[257.107971,211.740311],[252.893921,225.079178],[252.984283,246.551651],[228.806076,264.054565],[208.549286,257.233276],[194.496567,257.521667],[175.669449,263.928558],[151.044876,246.456955],[150.886841,222.486557],[148.382202,214.230164],[135.953033,197.447174],[146.958862,166.941818],[168.321396,160.497406],[175.89444,153.018646],[187.501587,136.256409],[216.357819,136.609344]]}}},{"ty":"fl","bm":0,"hd":false,"nm":"Fill","c":{"a":0,"k":[0.8824,0.8824,0.8824]},"r":1,"o":{"a":0,"k":100}},{"ty":"tr","a":{"a":0,"k":[0,0]},"s":{"a":0,"k":[100,100]},"sk":{"a":0,"k":0},"p":{"a":0,"k":[0,0]},"r":{"a":0,"k":0},"sa":{"a":0,"k":0},"o":{"a":0,"k":100}}]},{"ty":"gr","bm":0,"hd":false,"nm":"Group 2","it":[{"ty":"sh","bm":0,"hd":false,"nm":"Path 2","d":1,"ks":{"a":0,"k":{"c":false,"i":[[0,0],[10.505507999999992,3.7183840000000146],[14.470275,27.64222699999999],[2.9137269999999944,12.762466999999987],[-2.324776,12.338730000000027],[-14.028481,17.461730999999986],[-32.92851300000001,4.294739000000007],[-27.174239999999998,-22.328697000000005],[-4.368347999999969,-30.48461900000001],[21.884368999999992,-27.87269600000002],[29.12728900000002,-5.526580999999965],[11.001312000000013,-0.9042360000000258]],"o":[[-11.352874999999983,-2.6836250000000064],[-29.185974000000016,-10.32998699999996],[-6.054146000000003,-11.565093999999988],[-2.8687209999999936,-12.56530699999999],[4.056274000000002,-21.52868699999999],[20.879515999999995,-25.989441],[35.10136399999999,-4.578132999999994],[23.73269700000003,19.500823999999994],[5.02777100000003,35.086287999999996],[-18.341767000000004,23.360748],[-10.355452999999983,1.9648130000000492],[0,0]],"v":[[193.395996,319.876282],[160.314728,311.782837],[94.432755,254.961929],[81.612358,218.434753],[80.252663,181.001221],[105.713181,121.660965],[186.440628,76.066086],[280.357147,103.140884],[322.810883,178.789566],[297.394379,273.789795],[225.455032,316.870148],[193.395996,319.876282]]}}},{"ty":"sh","bm":0,"hd":false,"nm":"Path 3","d":1,"ks":{"a":0,"k":{"c":true,"i":[[0,0],[7.208159999999992,-9.766097999999985],[4.070754999999991,-5.436249000000004],[3.0496980000000065,-1.2484890000000064],[7.260955999999993,-1.5633700000000204],[-8.845756000000009,-11.151381999999984],[-3.8267060000000015,-5.804092999999995],[-0.11558600000000752,-2.805251999999996],[-0.21498099999999454,-7.9863129999999956],[-12.453460999999976,4.087432999999976],[-6.42437799999999,1.492432000000008],[-4.462707999999992,-1.007567999999992],[-6.786284999999992,-2.189270000000022],[-0.13186600000000226,12.72224399999999],[0.4151149999999859,7.135405999999989],[-3.1153100000000222,3.947525000000013],[-3.727661000000012,4.659255999999999],[9.92764299999999,5.772887999999995],[5.859526999999986,1.5537269999999808],[4.385528999999991,8.773818000000006],[3.508605999999986,5.092681999999996]],"o":[[-7.268234000000007,-9.711624000000015],[-4.034179999999992,5.46577400000001],[-2.1273350000000164,2.8409730000000195],[-6.857224000000002,2.807220000000001],[-13.832840000000004,2.9783789999999897],[4.326355000000007,5.4540250000000015],[1.5285800000000052,2.3184510000000103],[0.3287809999999922,7.978577000000001],[0.35572799999999916,13.215285999999992],[6.303406000000024,-2.068877999999984],[4.49588,-1.0444329999999695],[6.912338000000005,1.560608000000002],[12.102875000000012,3.9043889999999806],[0.07421899999999937,-7.15879799999999],[-0.29995700000000625,-5.155869000000024],[3.697022000000004,-4.6846769999999935],[7.163482999999985,-8.953842000000009],[-5.173430999999994,-3.0083159999999793],[-8.53422599999999,-2.2629540000000077],[-2.4191590000000076,-4.839783000000011],[0,0]],"v":[[216.162689,136.308151],[187.501587,136.256409],[175.89444,153.018646],[168.321396,160.497406],[146.958862,166.941818],[135.953033,197.447174],[148.382202,214.230164],[150.886841,222.486557],[151.044876,246.456955],[175.669449,263.928558],[194.496567,257.521667],[208.549286,257.233276],[228.806076,264.054565],[252.984283,246.551651],[252.893921,225.079178],[257.107971,211.740311],[267.978027,197.512009],[263.634277,170.348267],[246.529099,164.101379],[225.782745,150.444016],[216.162689,136.308151]]}}},{"ty":"fl","bm":0,"hd":false,"nm":"Fill","c":{"a":0,"k":[0.9686,0.9608,0.9608]},"r":1,"o":{"a":0,"k":100}},{"ty":"tr","a":{"a":0,"k":[0,0]},"s":{"a":0,"k":[100,100]},"sk":{"a":0,"k":0},"p":{"a":0,"k":[0,0]},"r":{"a":0,"k":0},"sa":{"a":0,"k":0},"o":{"a":0,"k":100}}]},{"ty":"gr","bm":0,"hd":false,"nm":"Group 3","it":[{"ty":"sh","bm":0,"hd":false,"nm":"Path 4","d":1,"ks":{"a":0,"k":{"c":false,"i":[[0,0],[-18.23618300000001,8.701034000000007],[-19.500320999999985,1.674163],[-25.658935000000014,-13.404376999999997],[-12.218170999999984,-43.137771999999984],[0.8837279999999623,-16.131286000000017],[21.257447000000013,-26.345214],[19.898010999999997,-9.800231999999994],[19.014556999999996,-1.7459409999999593],[19.646682999999996,5.781830000000014],[14.949211000000005,11.83520500000003],[8.580727000000003,34.05560299999996],[-0.9266999999999967,14.659104000000013],[-23.338077999999996,26.704491000000004],[-0.7808079999999933,1.1028510000000011]],"o":[[13.931342999999998,-15.031623999999994],[17.53823799999998,-8.368026999999998],[29.183258000000023,-2.5054739999999995],[39.51071200000001,20.640610000000002],[4.427153999999973,15.63052300000001],[-1.8413080000000264,33.60913099999999],[-13.993561,17.342773999999963],[-16.889404000000013,8.318450999999982],[-20.50276199999999,1.882630000000006],[-18.448211999999984,-5.429138000000023],[-27.48275799999999,-21.757994999999994],[-3.581581,-14.214752000000004],[2.2113610000000037,-34.98052899999999],[0.6505280000000084,-0.7443689999999918],[0,0]],"v":[[86.775055,94.822144],[134.518738,58.783356],[189.934769,43.827309],[272.255493,60.282661],[350.199677,155.973572],[355.878845,203.698898],[321.608032,293.912231],[270.769653,334.909058],[216.962265,350.184692],[156.978073,344.214203],[106.85878,318.100555],[52.630413,234.200104],[48.078472,190.78894],[84.871895,97.569908],[86.775055,94.822144]]}}},{"ty":"sh","bm":0,"hd":false,"nm":"Path 5","d":1,"ks":{"a":0,"k":{"c":true,"i":[[0,0],[-10.355452999999983,1.9648130000000492],[-18.341767000000004,23.360748],[5.02777100000003,35.086287999999996],[23.73269700000003,19.500823999999994],[35.10136399999999,-4.578132999999994],[20.879515999999995,-25.989441],[4.056274000000002,-21.52868699999999],[-2.8687209999999936,-12.56530699999999],[-6.054146000000003,-11.565093999999988],[-29.185974000000016,-10.32998699999996],[-11.810241999999988,-2.750824000000023]],"o":[[10.543945000000008,-0.9714350000000422],[29.12728900000002,-5.526580999999965],[21.884368999999992,-27.87269600000002],[-4.368347999999969,-30.48461900000001],[-27.174239999999998,-22.328697000000005],[-32.92851300000001,4.294739000000007],[-14.028481,17.461730999999986],[-2.324776,12.338730000000027],[2.9137269999999944,12.762466999999987],[14.470275,27.64222699999999],[10.505507999999992,3.7183840000000146],[0,0]],"v":[[193.853363,319.943481],[225.455032,316.870148],[297.394379,273.789795],[322.810883,178.789566],[280.357147,103.140884],[186.440628,76.066086],[105.713181,121.660965],[80.252663,181.001221],[81.612358,218.434753],[94.432755,254.961929],[160.314728,311.782837],[193.853363,319.943481]]}}},{"ty":"fl","bm":0,"hd":false,"nm":"Fill","c":{"a":0,"k":[0.8039,0.8039,0.8039]},"r":1,"o":{"a":0,"k":100}},{"ty":"tr","a":{"a":0,"k":[0,0]},"s":{"a":0,"k":[100,100]},"sk":{"a":0,"k":0},"p":{"a":0,"k":[0,0]},"r":{"a":0,"k":0},"sa":{"a":0,"k":0},"o":{"a":0,"k":100}}]},{"ty":"gr","bm":0,"hd":false,"nm":"Group 4","it":[{"ty":"sh","bm":0,"hd":false,"nm":"Path 6","d":1,"ks":{"a":0,"k":{"c":true,"i":[[0,0],[0.5056489999999982,-0.9472360000000037],[2.513803000000003,-23.948577],[-11.600103999999998,-28.851776],[-20.491455000000002,-19.06307899999996],[-25.807465000000008,-8.61508200000003],[-17.209960999999993,-1.1386720000000423],[-28.28246999999999,12.458587000000023],[-12.02502400000003,9.266723000000013],[-1.9212949999999864,0.9459219999999959],[17.67761200000001,-3.448822000000007],[9.601959000000022,-7.004669999999976],[4.732574,-3.974974999999972],[13.27363600000001,4.0468139999999835],[13.880630999999994,-4.362487999999985],[12.480362000000014,11.45562700000005],[15.90567,2.7597049999999967],[5.822936999999996,12.234527999999955],[9.885510000000004,7.818909000000019],[4.484558,3.279358000000002],[0.5561360000000022,11.258789000000036],[1.3822940000000017,7.064942000000002],[3.2611199999999982,8.108963000000017],[-0.9953249999999993,8.786651000000006],[-3.358378,5.793549000000013],[0.8457030000000003,17.167204999999996],[-5.419395999999999,5.868057000000007],[-5.366416000000001,4.884902999999994],[-1.7935829999999982,1.4237439999999992]],"o":[[0.3173490000000001,1.0828170000000057],[-11.410350999999999,21.375227999999993],[-3.2381209999999996,30.84903],[10.440494000000001,25.967636],[19.799605999999997,18.419434000000024],[16.294264999999996,5.4393309999999815],[30.98764,2.050231999999994],[13.932098999999994,-6.137177000000008],[1.4264220000000023,-1.0992439999999988],[-4.924468999999988,16.011810000000025],[-11.462311,2.236266999999998],[-4.995361000000003,3.6441649999999868],[-11.217697000000015,9.422028000000012],[-13.971907999999985,-4.259735000000035],[-16.021759000000003,5.035430000000019],[-11.772269999999992,-10.805694999999957],[-13.124084999999994,-2.27706900000004],[-5.157990000000005,-10.837463000000014],[-4.364651000000002,-3.452179000000001],[-9.350970999999998,-6.837983000000008],[-0.36132399999999976,-7.31487999999996],[-1.6645119999999984,-8.507353999999992],[-3.1976750000000003,-7.951217999999983],[0.7648450000000002,-6.751983999999993],[8.862376,-15.288527999999985],[-0.38067799999999963,-7.7275240000000025],[4.906009999999998,-5.312164999999993],[1.4506230000000002,-1.3204500000000081],[0,0]],"v":[[49.630531,88.019646],[49.892815,91.507401],[29.215628,159.714355],[41.790726,249.471573],[87.987122,317.353912],[156.250031,358.293518],[206.316925,368.173126],[294.925842,352.099091],[333.732727,328.889008],[338.765991,326.080872],[307.120514,357.941071],[274.90213,370.038483],[260.224213,381.388519],[223.080963,387.498016],[181.240997,387.106873],[139.061737,377.762146],[97.237465,357.883209],[68.891411,335.746185],[49.294033,305.762146],[36.407551,295.146973],[22.065723,267.701019],[21.667274,245.763351],[13.320373,220.916443],[6.233846,196.513947],[12.03259,176.762924],[22.111233,128.07309],[28.904873,106.797585],[44.878799,92.021782],[49.630531,88.019646]]}}},{"ty":"fl","bm":0,"hd":false,"nm":"Fill","c":{"a":0,"k":[0.8039,0.8039,0.8039]},"r":1,"o":{"a":0,"k":100}},{"ty":"tr","a":{"a":0,"k":[0,0]},"s":{"a":0,"k":[100,100]},"sk":{"a":0,"k":0},"p":{"a":0,"k":[0,0]},"r":{"a":0,"k":0},"sa":{"a":0,"k":0},"o":{"a":0,"k":100}}]},{"ty":"gr","bm":0,"hd":false,"nm":"Group 5","it":[{"ty":"sh","bm":0,"hd":false,"nm":"Path 7","d":1,"ks":{"a":0,"k":{"c":false,"i":[[0,0],[-3.6238930000000025,8.192367999999988],[-9.658951000000002,5.079437000000006],[-7.663458999999989,1.323990000000002],[-10.202453999999989,8.84064],[-14.850983000000014,-3.9813140000000002],[-8.355362000000014,0.002676999999998486],[-7.106842,2.080515000000001],[-10.743882000000013,-8.571484000000002],[-11.160460999999998,-2.6398600000000023],[-6.408111000000019,-1.5955200000000005],[-5.471466000000021,-13.015178000000006],[-9.970032000000003,-7.3550949999999915],[-3.003845999999953,-11.465073000000004],[0.3343810000000076,-4.090752000000009],[-8.543364999999994,-15.526611000000003],[6.689941999999974,-12.578613000000018],[0.8628230000000485,-9.968918000000002],[0.2553720000000226,-7.810241000000019],[4.635681000000034,-5.203552999999999],[5.9645080000000235,-4.446990999999969],[3.871063000000049,-9.223418999999978],[1.0721130000000016,-0.6873780000000238],[1.4264220000000023,-1.0992439999999988],[13.932098999999994,-6.137177000000008],[30.98764,2.050231999999994],[16.294264999999996,5.4393309999999815],[19.799605999999997,18.419434000000024],[10.440494000000001,25.967636],[-3.2381209999999996,30.84903],[-11.410350999999999,21.375227999999993],[0.005172999999999206,1.2199250000000035]],"o":[[7.191017000000002,-5.653167999999994],[4.218154999999996,-9.535774000000004],[6.851882000000003,-3.6032559999999947],[13.894265000000004,-2.4004739999999956],[11.655304000000001,-10.099568999999999],[8.097183000000001,2.170726],[7.323439999999977,-0.0023460000000010695],[13.84278900000001,-4.05244],[8.56854199999998,6.835987999999999],[6.426452999999981,1.5200999999999993],[14.66293300000001,3.650841],[4.667693999999983,11.103127],[8.693633999999975,6.413468000000009],[1.0593260000000555,4.043205],[-1.4562990000000013,17.81546],[6.991851999999994,12.706970000000013],[-4.6260070000000155,8.697936999999996],[-0.6721499999999878,7.765456999999998],[-0.22589099999999007,6.909515999999996],[-4.960387999999966,5.567993000000001],[-8.005889999999965,5.968995000000007],[-0.2438659999999686,0.5810549999999921],[-2.243926999999985,1.088011999999992],[-12.02502400000003,9.266723000000013],[-28.28246999999999,12.458587000000023],[-17.209960999999993,-1.1386720000000423],[-25.807465000000008,-8.61508200000003],[-20.491455000000002,-19.06307899999996],[-11.600103999999998,-28.851776],[2.513803000000003,-23.948577],[0.5056489999999982,-0.9472360000000037],[0,0]],"v":[[49.942707,87.882538],[65.040794,66.380981],[83.11657,41.7253],[105.452148,34.432041],[140.530945,15.854121],[179.847473,7.210122],[204.8685,10.721106],[226.799713,6.844898],[262.901337,15.343652],[290.807617,32.379871],[310.063629,37.038589],[337.984436,64.419189],[359.159821,92.2276],[380.155518,116.71299],[381.863098,129.181015],[392.984039,178.961624],[392.559753,216.931213],[382.393921,244.376587],[381.960876,267.811981],[375.571716,286.730164],[359.200653,302.062286],[340.928528,324.206848],[339.088623,325.938782],[333.732727,328.889008],[294.925842,352.099091],[206.316925,368.173126],[156.250031,358.293518],[87.987122,317.353912],[41.790726,249.471573],[29.215628,159.714355],[49.892815,91.507401],[49.942707,87.882538]]}}},{"ty":"sh","bm":0,"hd":false,"nm":"Path 8","d":1,"ks":{"a":0,"k":{"c":true,"i":[[0,0],[0.6505280000000084,-0.7443689999999918],[2.2113610000000037,-34.98052899999999],[-3.581581,-14.214752000000004],[-27.48275799999999,-21.757994999999994],[-18.448211999999984,-5.429138000000023],[-20.50276199999999,1.882630000000006],[-16.889404000000013,8.318450999999982],[-13.993561,17.342773999999963],[-1.8413080000000264,33.60913099999999],[4.427153999999973,15.63052300000001],[39.51071200000001,20.640610000000002],[29.183258000000023,-2.5054739999999995],[17.53823799999998,-8.368026999999998],[14.156989999999993,-15.306762000000006]],"o":[[-0.5551609999999982,0.8277129999999886],[-23.338077999999996,26.704491000000004],[-0.9266999999999967,14.659104000000013],[8.580727000000003,34.05560299999996],[14.949211000000005,11.83520500000003],[19.646682999999996,5.781830000000014],[19.014556999999996,-1.7459409999999593],[19.898010999999997,-9.800231999999994],[21.257447000000013,-26.345214],[0.8837279999999623,-16.131286000000017],[-12.218170999999984,-43.137771999999984],[-25.658935000000014,-13.404376999999997],[-19.500320999999985,1.674163],[-18.23618300000001,8.701034000000007],[0,0]],"v":[[86.549408,95.097282],[84.871895,97.569908],[48.078472,190.78894],[52.630413,234.200104],[106.85878,318.100555],[156.978073,344.214203],[216.962265,350.184692],[270.769653,334.909058],[321.608032,293.912231],[355.878845,203.698898],[350.199677,155.973572],[272.255493,60.282661],[189.934769,43.827309],[134.518738,58.783356],[86.549408,95.097282]]}}},{"ty":"fl","bm":0,"hd":false,"nm":"Fill","c":{"a":0,"k":[0.8824,0.8824,0.8824]},"r":1,"o":{"a":0,"k":100}},{"ty":"tr","a":{"a":0,"k":[0,0]},"s":{"a":0,"k":[100,100]},"sk":{"a":0,"k":0},"p":{"a":0,"k":[0,0]},"r":{"a":0,"k":0},"sa":{"a":0,"k":0},"o":{"a":0,"k":100}}]}],"ind":1}]}]}